{
"meta":{"test_sets":[],"test_metrics":[],"learn_metrics":[{"best_value":"Min","name":"RMSE"}],"launch_mode":"Train","parameters":"","iteration_count":1000,"learn_sets":["learn"],"name":"experiment"},
"iterations":[
{"learn":[0.952731204],"iteration":0,"passed_time":0.2072036888,"remaining_time":206.9964851,,
{"learn":[0.9247958322],"iteration":1,"passed_time":0.2595879433,"remaining_time":129.534383,
{"learn":[0.9313615525],"iteration":2,"passed_time":0.3022766758,"remaining_time":100.4566153},
,
{"learn":[0.8805826195],"iteration":3,"passed_time":0.3581273183,"remaining_time":89.173702,,,
,
{"learn":[0.8935830296],"iteration":4,"passed_time":0.4134208509,"remaining_time":82.2707,,
,
,
{"learn":[0.8787125038],"iteration":5,"passed_time":0.4625488269,"remaining_time":76.628,
{",
{"learn":[0.8369933445],"iteration":6,"passed_time":0.5176635833,"remaining_time":73.4342,
{"l,
,
{"learn":[0.8533604599],"iteration":7,"passed_time":0.5677503165,"remaining_time":70.40,
{"l,
{"learn":[0.8157429767],"iteration":8,"passed_time":0.6238034539,"remaining_time":68.6876,
{"l,
{"learn":[0.806780728],"iteration":9,"passed_time":0.6755016769,"remaining_time":66.87466,
{",
{"learn":[0.7998213791],"iteration":10,"passed_time":0.7229395228,"remaining_time":64.99883,
{,,
{"learn":[0.7933647058],"iteration":11,"passed_time":0.7704865933,"remaining_time":63.43672,
{,,
{"learn":[0.7869150101],"iteration":12,"passed_time":0.8151486779,"remaining_time":61.88859,
{,,
{"learn":[0.7823957534],"iteration":13,"passed_time":0.8472857832,"remaining_time":59.6731,
{",
{"learn":[0.7969300613],"iteration":14,"passed_time":0.8952656787,"remaining_time":58.7891129},,
{,,
{"learn":[0.7989233551],"iteration":15,"passed_time":0.9492612735,"remaining_time":58.3795,,
{,,
{"learn":[0.795760906],"iteration":16,"passed_time":1.000119382,"remaining_time":57.830,
{"l,
{"learn":[0.7927996664],"iteration":17,"passed_time":1.044387739,"remaining_time":56.977,
{"le,
{"learn":[0.7903323611],"iteration":18,"passed_time":1.095465855,"remaining_time":56.560,
{"learn":[0.7798966378],"iteration":19,"passed_time":1.156541228,"remaining_time":56.67052017},
{"le,
{"learn":[0.7844931119],"iteration":20,"passed_time":1.208205796,"remaining_time":56.3,
{"lear,
{"learn":[0.7822622116],"iteration":21,"passed_time":1.253171053,"remaining_time":55.7,
{"lear,
{"learn":[0.7806606087],"iteration":22,"passed_time":1.299379963,"remaining_time":55.1,
{"lear,
{"learn":[0.7785436624],"iteration":23,"passed_time":1.348777124,"remaining_time":54.,
{"learn":[0.7687861862],"iteration":24,"passed_time":1.400080596,"remaining_time":54.60314326},
{"l,,
{"learn":[0.7621588039],"iteration":25,"passed_time":1.460897515,"remaining_time":54.727,
{",
,,
{"learn":[0.7730514061],"iteration":26,"passed_time":1.490637603,"remaining_time":53.71,
{",
,
{"learn":[0.7716637785],"iteration":27,"passed_time":1.538819155,"remaining_time":53.419,
{"le,
{"learn":[0.7702848549],"iteration":28,"passed_time":1.584189222,"remaining_time":53.043,
{"le,
{"learn":[0.7690966526],"iteration":29,"passed_time":1.637883177,"remaining_time":52.958,
{"le,
{"learn":[0.7679458775],"iteration":30,"passed_time":1.689331804,"remaining_time":52.805,
{"le,
{"learn":[0.7668612678],"iteration":31,"passed_time":1.747162292,"remaining_time":52.851,
{"le,
{"learn":[0.7652920573],"iteration":32,"passed_time":1.803547869,"remaining_time":52.849,
{",
,
{"learn":[0.764369791],"iteration":33,"passed_time":1.854196691,"remaining_time":52.6810,
,
{"learn":[0.7499790511],"iteration":34,"passed_time":1.902948697,"remaining_time":52.467014,
{,
{"learn":[0.7489015308],"iteration":35,"passed_time":1.954262274,"remaining_time":52.330800,
,
{,
{"learn":[0.7613567763],"iteration":36,"passed_time":1.996700257,"remaining_time":51.968,
,,
{,
{"learn":[0.7606408238],"iteration":37,"passed_time":2.041462608,"remaining_time":51.681,
,
{",
{"learn":[0.7600261982],"iteration":38,"passed_time":2.088052318,"remaining_time":51.451,,,
{"learn":[0.7456874276],"iteration":39,"passed_time":2.152695695,"remaining_time":51.664696,
,
{"learn":[0.7282761276],"iteration":40,"passed_time":2.176006972,"remaining_time":50.897333,
{,
{",
{"learn":[0.7574748128],"iteration":41,"passed_time":2.239931122,"remaining_time":51.0,
{",
{",
{"learn":[0.7570002494],"iteration":42,"passed_time":2.288200121,"remaining_time":50.9,
{,
{"l,
{"learn":[0.7562433414],"iteration":43,"passed_time":2.335654976,"remaining_time":50,
{"l,
{"l,
{"learn":[0.7557145481],"iteration":44,"passed_time":2.375891355,"remaining_time":50,
{"l,
{,,
{"learn":[0.7549288743],"iteration":45,"passed_time":2.421109653,"remaining_time":50.,
{"learn,
{"learn":[0.7544440066],"iteration":46,"passed_time":2.476985368,"remaining_time":50.,
{"learn,
{"learn":[0.7534935652],"iteration":47,"passed_time":2.525223462,"remaining_time":50,
{"learn",
{"learn":[0.752932093],"iteration":48,"passed_time":2.573717087,"remaining_time":49.,
{"learn,
{"learn":[0.7523962734],"iteration":49,"passed_time":2.623473315,"remaining_time":49.,
{"learn,
{"learn":[0.7518498002],"iteration":50,"passed_time":2.669339328,"remaining_time":49.,
{"learn,
{"learn":[0.7513133559],"iteration":51,"passed_time":2.723176708,"remaining_time":4,
{",
{"lea,
{"learn":[0.7509813589],"iteration":52,"passed_time":2.765931669,"remaining_time":4,
{",
{"lea,
{"learn":[0.7504844157],"iteration":53,"passed_time":2.812788221,"remaining_time":4,
{",
{"lea,
{"learn":[0.7494229474],"iteration":54,"passed_time":2.856854095,"remaining_time":4,
{"learn":,
{"learn":[0.7483054509],"iteration":55,"passed_time":2.904719409,"remaining_time":4,
{"learn":,
{"learn":[0.7479782644],"iteration":56,"passed_time":2.95841218,"remaining_time":48,
{"learn",
{"learn":[0.7476591031],"iteration":57,"passed_time":3.005889473,"remaining_time":,
,
{"learn",
{"learn":[0.7470604631],"iteration":58,"passed_time":3.045977324,"remaining_time":,
,
{"learn",
{"learn":[0.746825017],"iteration":59,"passed_time":3.093160931,"remaining_time":4,
,
{"learn,
{"learn":[0.7455422082],"iteration":60,"passed_time":3.136463167,"remaining_time":,
{,
{"lear,
{"learn":[0.7453155986],"iteration":61,"passed_time":3.187614526,"remaining_time":4,
{"learn":,
{"learn":[0.7450081992],"iteration":62,"passed_time":3.240310165,"remaining_time":4,
{"learn":,
{"learn":[0.7446603563],"iteration":63,"passed_time":3.282303726,"remaining_time":4,
{"learn":,
{"learn":[0.7444546207],"iteration":64,"passed_time":3.32471697,"remaining_time":47,
{"learn",
{"learn":[0.7442512893],"iteration":65,"passed_time":3.38125743,"remaining_time":47.84991575},
{"learn":[0.7440700283],"iteration":66,"passed_time":3.424604548,"remaining_time":47.68889617},
{"learn":[0.7439039413],"iteration":67,"passed_time":3.460159936,"remaining_time":47.,
{"learn,
{"learn":[0.742993397],"iteration":68,"passed_time":3.502191767,"remaining_time":47.2,
{"lear,
{"learn":[0.7425760485],"iteration":69,"passed_time":3.550209438,"remaining_time":47.1,
{"lear,
{"learn":[0.7419315168],"iteration":70,"passed_time":3.598861964,"remaining_time":47.0,
{"lear,
{"learn":[0.7417867235],"iteration":71,"passed_time":3.642695375,"remaining_time":46.9,
{"lear,
{"learn":[0.7414353993],"iteration":72,"passed_time":3.689175187,"remaining_time":46.,
{"learn,
{"learn":[0.7412734304],"iteration":73,"passed_time":3.731252298,"remaining_time":46.,
{"learn,
{"learn":[0.7410073814],"iteration":74,"passed_time":3.784766408,"remaining_time":46.,
{"lear,
{"learn":[0.7406431205],"iteration":75,"passed_time":3.840346756,"remaining_time":46.6,
{"lear,
{"learn":[0.7403957237],"iteration":76,"passed_time":3.888180488,"remaining_time":46.6,
{"lear,
{"learn":[0.7402702282],"iteration":77,"passed_time":3.933643059,"remaining_time":46.,,
{"lear,
{"learn":[0.7400490976],"iteration":78,"passed_time":3.97187154,"remaining_time":46.,
,
{"lea,
{"learn":[0.7395559827],"iteration":79,"passed_time":4.020415696,"remaining_time":46.,
,
{"lea,
{"learn":[0.7390033333],"iteration":80,"passed_time":4.076599815,"remaining_time":46,
{,
{"lea,
{"learn":[0.7385663877],"iteration":81,"passed_time":4.131232296,"remaining_time":46.2,
{"lear,
{"learn":[0.7383889583],"iteration":82,"passed_time":4.180936997,"remaining_time":46.1,
{"lear,
{"learn":[0.7381740669],"iteration":83,"passed_time":4.232038401,"remaining_time":46.1,
{"lear,
{"learn":[0.7378649149],"iteration":84,"passed_time":4.276249245,"remaining_time":46.0,
{"lear,
{"learn":[0.7374411236],"iteration":85,"passed_time":4.323515085,"remaining_time":45.9,
{"lear,
{"learn":[0.7373052986],"iteration":86,"passed_time":4.369499103,"remaining_time":45.8,
{"lear,
{"learn":[0.7369804585],"iteration":87,"passed_time":4.412002537,"remaining_time":45.7,
{"lear,
{"learn":[0.7366830414],"iteration":88,"passed_time":4.456843087,"remaining_time":45.6,
{"lear,
{"learn":[0.7362803662],"iteration":89,"passed_time":4.507905059,"remaining_time":45.5,
{"lear,
{"learn":[0.7361709282],"iteration":90,"passed_time":4.544086183,"remaining_time":45.3,
{"lear,
{"learn":[0.7359944691],"iteration":91,"passed_time":4.589799176,"remaining_time":45.2,
{"lea,
{"learn":[0.7358316573],"iteration":92,"passed_time":4.630126119,"remaining_time":45.15,
{"lea,
{"learn":[0.7353325757],"iteration":93,"passed_time":4.671975155,"remaining_ti,
{"learn,
{"lea,
{"learn":[0.7351519164],"iteration":94,"passed_time":4.71220877,"remaining_tim,
{"learn,
{"le,
{"learn":[0.7349900494],"iteration":95,"passed_time":4.76106717,"remaining_time":44.8333,
{"l,
{"learn":[0.7348497881],"iteration":96,"passed_time":4.802955754,"remaining_time":44.712,
{"le,
{"learn":[0.7344273689],"iteration":97,"passed_time":4.849036809,"remaining_time":44.630,
{"le,
{"learn":[0.734075213],"iteration":98,"passed_time":4.896979625,"remaining_time":44.5674,
{"l,
{"learn":[0.7336149238],"iteration":99,"passed_time":4.951895804,"remaining_time":44.5670,
{"l,
{"learn":[0.7334238341],"iteration":100,"passed_time":4.995834308,"remaining_time":44.4678,
{"l,
{"learn":[0.7331651667],"iteration":101,"passed_time":5.04018087,"remaining_time":44.37335,
{",
{"learn":[0.7329384592],"iteration":102,"passed_time":5.081415231,"remaining_time":44.25271,
{",
{"learn":[0.7327073842],"iteration":103,"passed_time":5.121709466,"remaining_time":44.12549,
{",
{"learn":[0.732484239],"iteration":104,"passed_time":5.165213235,"remaining_time":44.027293,
{"learn":[0.7224197805],"iteration":105,"passed_time":5.197666213,"remaining_time":43.8369207},
{"learn":[0.7220243845],"iteration":106,"passed_time":5.247307261,"remaining_time":43.79294751},
{"learn":[0.7216223477],"iteration":107,"passed_time":5.303091791,"remaining_time":43.79960998},
{"learn":[0.7212217403],"iteration":108,"passed_time":5.34369059,"remaining_time":43.68099372},
{"learn":[0.7210604823],"iteration":109,"passed_time":5.3886484,"remaining_time":43.59906433},
,
{"learn":[0.731255256],"iteration":110,"passed_time":5.458372857,"remaining_time":43.7161573,
,
{"learn":[0.7310963767],"iteration":111,"passed_time":5.501662846,"remaining_time":43.6203268,
,
{"learn":[0.7307430276],"iteration":112,"passed_time":5.544738649,"remaining_time":43.5237449,
,
{"learn":[0.7305981843],"iteration":113,"passed_time":5.589395533,"remaining_time":43.4403898,
,
{"learn":[0.7303173445],"iteration":114,"passed_time":5.633126058,"remaining_time":43.3505788,,
{"learn":[0.7301466179],"iteration":115,"passed_time":5.675231175,"remaining_time":43.249175,
{,
{"learn":[0.7299738605],"iteration":116,"passed_time":5.714870403,"remaining_time":43.13017,
{",
{"learn":[0.72976207],"iteration":117,"passed_time":5.737428935,"remaining_time":42.8848501,
,
{"learn":[0.7294034509],"iteration":118,"passed_time":5.761327314,"remaining_time":42.6531879,
,
{"learn":[0.7291888206],"iteration":119,"passed_time":5.782931781,"remaining_time":42.4081663,
,
{"learn":[0.7289706822],"iteration":120,"passed_time":5.802588409,"remaining_time":42.1526877,
{"learn":[0.7172290735],"iteration":121,"passed_time":5.827367503,"remaining_time":41.9379399},
{"learn":[0.7171242205],"iteration":122,"passed_time":5.868856023,"remaining_time":41.84542058},
{"learn":[0.7169094506],"iteration":123,"passed_time":5.917682833,"remaining_time":41.80556582},
{"learn":[0.7167088305],"iteration":124,"passed_time":5.969538146,"remaining_time":41.7867670,
,
{"learn":[0.7165348039],"iteration":125,"passed_time":6.017276912,"remaining_time":41.738889,
{,
{"learn":[0.7163431543],"iteration":126,"passed_time":6.058175549,"remaining_time":41.643994,
{,
{"learn":[0.7157489194],"iteration":127,"passed_time":6.097610584,"remaining_time":41.53997,
{,
{"learn":[0.7155155264],"iteration":128,"passed_time":6.147725887,"remaining_time":41.509063,
{,
{"learn":[0.7152810175],"iteration":129,"passed_time":6.196077848,"remaining_time":41.46605,
{",
{"learn":[0.7147540821],"iteration":130,"passed_time":6.257431979,"remaining_time":41.50922,
{",
{"learn":[0.7141223714],"iteration":131,"passed_time":6.296478847,"remaining_time":41.40411,
{",
{"learn":[0.7139507941],"iteration":132,"passed_time":6.341898683,"remaining_time":41.34155,
{",
{"learn":[0.7136456849],"iteration":133,"passed_time":6.380283255,"remaining_time":41.23377,
{",
{"learn":[0.7134014866],"iteration":134,"passed_time":6.404428992,"remaining_time":41.03578,
{"learn":[0.7264237693],"iteration":135,"passed_time":6.433843691,"remaining_time":40.87383051},
{"learn":[0.7263695097],"iteration":136,"passed_time":6.458213597,"remaining_time":40.68203164},
{"learn":[0.7253591418],"iteration":137,"passed_time":6.482865235,"remaining_time":40.49441908},
{"learn":[0.7251662435],"iteration":138,"passed_time":6.512262095,"remaining_time":40.33854434},
{"learn":[0.7249897645],"iteration":139,"passed_time":6.540083525,"remaining_time":40.1747988},
{"learn":[0.7248408266],"iteration":140,"passed_time":6.566018954,"remaining_time":40.00149136},
{,
{"learn":[0.7119119384],"iteration":141,"passed_time":6.583652417,"remaining_time":39.780097,,
{"learn":[0.711768534],"iteration":142,"passed_time":6.607620901,"remaining_time":39.59951827},
{"learn":[0.7116515351],"iteration":143,"passed_time":6.64335014,"remaining_time":39.49102583},
{"learn":[0.7114868301],"iteration":144,"passed_time":6.6799245,"remaining_time":39.38852033},
{"learn":[0.7112765485],"iteration":145,"passed_time":6.711756973,"remaining_time":39.2591812},
{"learn":[0.7111294142],"iteration":146,"passed_time":6.738944584,"remaining_time":39.10421585},
{"learn":[0.7109908605],"iteration":147,"passed_time":6.786090857,"remaining_time":39.06587439},
{"learn":[0.7109646665],"iteration":148,"passed_time":6.80976457,"remaining_time":38.89335335},
{"learn":[0.7108659505],"iteration":149,"passed_time":6.83102483,"remaining_time":38.70914071},
{"learn":[0.7107135022],"iteration":150,"passed_time":6.854972598,"remaining_time":38.54219693},
{"learn":[0.7104413323],"iteration":151,"passed_time":6.876785906,"remaining_time":38.36522663},
{"learn":[0.7101960503],"iteration":152,"passed_time":6.898932854,"remaining_time":38.19213155},
{"learn":[0.709856762],"iteration":153,"passed_time":6.924570472,"remaining_time":38.04017285},
{"learn":[0.7094418271],"iteration":154,"passed_time":6.950137192,"remaining_time":37.88945759},
{"learn":[0.7092868631],"iteration":155,"passed_time":6.976108255,"remaining_time":37.7425344},
{"learn":[0.7091828167],"iteration":156,"passed_time":7.003520064,"remaining_time":37.60488798},
{"learn":[0.708955351],"iteration":157,"passed_time":7.028070384,"remaining_time":37.45338774},
{"learn":[0.708680931],"iteration":158,"passed_time":7.053505948,"remaining_time":37.30816668},
{"learn":[0.708562782],"iteration":159,"passed_time":7.069736908,"remaining_time":37.11611877},
{"learn":[0.7084257829],"iteration":160,"passed_time":7.099362772,"remaining_time":36.99605817},
{"learn":[0.708314622],"iteration":161,"passed_time":7.202640668,"remaining_time":37.25810419},
{"learn":[0.7081972556],"iteration":162,"passed_time":7.22727503,"remaining_time":37.11183558},
{"learn":[0.7078250111],"iteration":163,"passed_time":7.252402387,"remaining_time":36.96956339},
{"learn":[0.7076080044],"iteration":164,"passed_time":7.321496035,"remaining_time":37.05120721},
{"learn":[0.7075358822],"iteration":165,"passed_time":7.341728804,"remaining_time":36.88555315},
{"learn":[0.707534154],"iteration":166,"passed_time":7.358679544,"remaining_time":36.70526982},
{"learn":[0.7073232197],"iteration":167,"passed_time":7.382047494,"remaining_time":36.5587114},
{"learn":[0.7072694243],"iteration":168,"passed_time":7.401175877,"remaining_time":36.39276422},
{"learn":[0.7072210134],"iteration":169,"passed_time":7.429086415,"remaining_time":36.27142191},
{"learn":[0.7069726978],"iteration":170,"passed_time":7.452008346,"remaining_time":36.12698783},
{"learn":[0.7068031881],"iteration":171,"passed_time":7.473557309,"remaining_time":35.97735728},
{"learn":[0.7066166775],"iteration":172,"passed_time":7.497710911,"remaining_time":35.84165852},
{"learn":[0.7065958892],"iteration":173,"passed_time":7.517195641,"remaining_time":35.68507816},
{"learn":[0.7064125753],"iteration":174,"passed_time":7.539956764,"remaining_time":35.54551046},
{"learn":[0.7062908584],"iteration":175,"passed_time":7.563247732,"remaining_time":35.40975075},
{"learn":[0.7061429214],"iteration":176,"passed_time":7.58326102,"remaining_time":35.26002158},
{"learn":[0.7058632561],"iteration":177,"passed_time":7.608772388,"remaining_time":35.1371399},
{"learn":[0.7057267196],"iteration":178,"passed_time":7.630625943,"remaining_time":34.99856927},
{"learn":[0.7055204744],"iteration":179,"passed_time":7.655225266,"remaining_time":34.87380399},
{"learn":[0.7054284795],"iteration":180,"passed_time":7.67694357,"remaining_time":34.7371093},
{"learn":[0.7049824859],"iteration":181,"passed_time":7.697724765,"remaining_time":34.59746625},
{"learn":[0.7048241245],"iteration":182,"passed_time":7.72115823,"remaining_time":34.47096324},
{"learn":[0.7046654067],"iteration":183,"passed_time":7.745897346,"remaining_time":34.35137084},
{"learn":[0.7043995232],"iteration":184,"passed_time":7.769285984,"remaining_time":34.22685447},
{"learn":[0.7040329262],"iteration":185,"passed_time":7.796819432,"remaining_time":34.12156461},
{"learn":[0.7038506119],"iteration":186,"passed_time":7.818945083,"remaining_time":33.99359547},
{"learn":[0.7036533743],"iteration":187,"passed_time":7.842375862,"remaining_time":33.87238936},
{"learn":[0.7035315931],"iteration":188,"passed_time":7.864119512,"remaining_time":33.74497844},
{"learn":[0.7034471915],"iteration":189,"passed_time":7.88534296,"remaining_time":33.61646209},
{"learn":[0.7033551734],"iteration":190,"passed_time":7.908263045,"remaining_time":33.49625551},
{"learn":[0.7031416082],"iteration":191,"passed_time":7.93166153,"remaining_time":33.37907561},
{"learn":[0.7029618975],"iteration":192,"passed_time":7.953382812,"remaining_time":33.25585455},
{"learn":[0.7020565792],"iteration":193,"passed_time":7.977772061,"remaining_time":33.14476433},
{"learn":[0.7018773837],"iteration":194,"passed_time":7.998072976,"remaining_time":33.01768587},
{"learn":[0.7017059103],"iteration":195,"passed_time":8.020157725,"remaining_time":32.89901434},
{"learn":[0.7015370698],"iteration":196,"passed_time":8.044659651,"remaining_time":32.79117614},
{"learn":[0.7014411755],"iteration":197,"passed_time":8.068725995,"remaining_time":32.68241539},
{"learn":[0.7008045547],"iteration":198,"passed_time":8.092032496,"remaining_time":32.57144738},
{"learn":[0.7006906865],"iteration":199,"passed_time":8.113419765,"remaining_time":32.45367906},
{"learn":[0.7005720737],"iteration":200,"passed_time":8.136494353,"remaining_time":32.34357705},,
{"learn":[0.7134518101],"iteration":201,"passed_time":8.19099753,"remaining_time":32.35849519,,
{"learn":[0.7133746186],"iteration":202,"passed_time":8.212064167,"remaining_time":32.2414539},
{"learn":[0.7124933569],"iteration":203,"passed_time":8.237195251,"remaining_time":32.14121284},
{"learn":[0.7122286768],"iteration":204,"passed_time":8.262761766,"remaining_time":32.04339319},
{"learn":[0.7120770959],"iteration":205,"passed_time":8.287713275,"remaining_time":31.94390456},
{"learn":[0.7119992835],"iteration":206,"passed_time":8.312600445,"remaining_time":31.84488963,,
{"learn":[0.7119051533],"iteration":207,"passed_time":8.341810517,"remaining_time":31.76304774,,
{"learn":[0.7117598613],"iteration":208,"passed_time":8.365960116,"remaining_time":31.6625571,
,
{"learn":[0.7117060436],"iteration":209,"passed_time":8.388798349,"remaining_time":31.5578604,
,
{"learn":[0.711616434],"iteration":210,"passed_time":8.413896319,"remaining_time":31.46238955,,
{"learn":[0.711511709],"iteration":211,"passed_time":8.434588923,"remaining_time":31.35120789},
{"learn":[0.7114487074],"iteration":212,"passed_time":8.456154362,"remaining_time":31.24410086},
{"learn":[0.7113735908],"iteration":213,"passed_time":8.475807817,"remaining_time":31.13077077},
{"learn":[0.7112627258],"iteration":214,"passed_time":8.496778174,"remaining_time":31.02312031,,
{"learn":[0.7110847796],"iteration":215,"passed_time":8.521204527,"remaining_time":30.92881643,,
{"learn":[0.7109740434],"iteration":216,"passed_time":8.540608121,"remaining_time":30.81703299,,
{"learn":[0.710770092],"iteration":217,"passed_time":8.566964523,"remaining_time":30.7310378,
,
{"learn":[0.7106457016],"iteration":218,"passed_time":8.589698138,"remaining_time":30.63266,
{",
{"learn":[0.7105672098],"iteration":219,"passed_time":8.613880059,"remaining_time":30.54012,
{",
{"learn":[0.7104935048],"iteration":220,"passed_time":8.634363565,"remaining_time":30.43515,
{",
{"learn":[0.7104212165],"iteration":221,"passed_time":8.657259558,"remaining_time":30.33940,
{",
{"learn":[0.710330638],"iteration":222,"passed_time":8.678122302,"remaining_time":30.2372,
{"l,
{"learn":[0.7097822041],"iteration":223,"passed_time":8.700006803,"remaining_time":30.1393,
{"l,
{"learn":[0.7095529447],"iteration":224,"passed_time":8.721471455,"remaining_time":30.0406,
{",
{"learn":[0.7092465455],"iteration":225,"passed_time":8.742839884,"remaining_time":29.94229,
{",
{"learn":[0.7092009259],"iteration":226,"passed_time":8.766928228,"remaining_time":29.85390,
{",
{"learn":[0.7091818452],"iteration":227,"passed_time":8.787723218,"remaining_time":29.75492,
{",
{"learn":[0.7090659431],"iteration":228,"passed_time":8.807980899,"remaining_time":29.65481,
{",
{"learn":[0.7087244232],"iteration":229,"passed_time":8.830500428,"remaining_time":29.5629,
{"learn":[0.6964385986],"iteration":230,"passed_time":8.819385821,"remaining_time":29.35977358},
{",
{"learn":[0.7084047687],"iteration":231,"passed_time":8.873466012,"remaining_time":29.37423,
{"learn":[0.6962584107],"iteration":232,"passed_time":8.864931717,"remaining_time":29.18198552},
{"learn":[0.6959508598],"iteration":233,"passed_time":8.887654056,"remaining_time":29.09377353},
{"learn":[0.6958949654],"iteration":234,"passed_time":8.909321487,"remaining_time":29.00268484},
{"learn":[0.6955289486],"iteration":235,"passed_time":8.933966657,"remaining_time":28.92182426},
{"learn":[0.6954988844],"iteration":236,"passed_time":8.953110225,"remaining_time":28.82372617},
{"learn":[0.6954028864],"iteration":237,"passed_time":8.977844898,"remaining_time":28.74419249},
{"learn":[0.695330602],"iteration":238,"passed_time":9.002172776,"remaining_time":28.6638221},
{"learn":[0.6952113542],"iteration":239,"passed_time":9.030589554,"remaining_time":28.59686692},
{"learn":[0.6950920515],"iteration":240,"passed_time":9.055608851,"remaining_time":28.51953161},
{"learn":[0.6950204108],"iteration":241,"passed_time":9.077954099,"remaining_time":28.43425292},
{"learn":[0.6947420063],"iteration":242,"passed_time":9.099150944,"remaining_time":28.34591467},
{"learn":[0.6946249108],"iteration":243,"passed_time":9.120537879,"remaining_time":28.25871572},
{"learn":[0.6945819891],"iteration":244,"passed_time":9.139707033,"remaining_time":28.16521963},
{"learn":[0.6943040556],"iteration":245,"passed_time":9.158645973,"remaining_time":28.07162221},
{"learn":[0.6942033375],"iteration":246,"passed_time":9.179674023,"remaining_time":27.98499814},
{"learn":[0.6941612214],"iteration":247,"passed_time":9.200216633,"remaining_time":27.89743108},
{"learn":[0.694084194],"iteration":248,"passed_time":9.223437978,"remaining_time":27.81848161},
{"learn":[0.6940178433],"iteration":249,"passed_time":9.24138405,"remaining_time":27.72415215},
{"learn":[0.6938713497],"iteration":250,"passed_time":9.262372466,"remaining_time":27.63950987},
{"learn":[0.6937483477],"iteration":251,"passed_time":9.28404283,"remaining_time":27.55739697},
{"learn":[0.6935643317],"iteration":252,"passed_time":9.303191855,"remaining_time":27.46831745},
{"learn":[0.6933814711],"iteration":253,"passed_time":9.324597251,"remaining_time":27.38641555},
{"learn":[0.6933123483],"iteration":254,"passed_time":9.347753264,"remaining_time":27.31010267},
{"learn":[0.6932318381],"iteration":255,"passed_time":9.371389354,"remaining_time":27.23560031},
{"learn":[0.6931419826],"iteration":256,"passed_time":9.39245059,"remaining_time":27.15404976},
{"learn":[0.6930631427],"iteration":257,"passed_time":9.414339719,"remaining_time":27.07534911},
{"learn":[0.6930206952],"iteration":258,"passed_time":9.432475784,"remaining_time":26.98634964},
{"learn":[0.6929390183],"iteration":259,"passed_time":9.453724273,"remaining_time":26.9067537},
{",
{"learn":[0.7042903227],"iteration":260,"passed_time":9.509051414,"remaining_time":26.924,
{"le,
{"learn":[0.7041520852],"iteration":261,"passed_time":9.529463248,"remaining_time":26.842,
{"learn":[0.6917564932],"iteration":262,"passed_time":9.519006867,"remaining_time":26.67493559},
{"learn":[0.6916173956],"iteration":263,"passed_time":9.54477987,"remaining_time":26.60968933},
{"learn":[0.6915643162],"iteration":264,"passed_time":9.56362152,"remaining_time":26.52551629},
{"learn":[0.69151763],"iteration":265,"passed_time":9.586885211,"remaining_time":26.45403663},
{"learn":[0.6913184927],"iteration":266,"passed_time":9.608570776,"remaining_time":26.37858569},
{"learn":[0.6912551515],"iteration":267,"passed_time":9.629104259,"remaining_time":26.30038925},
{"learn":[0.6911305665],"iteration":268,"passed_time":9.651120634,"remaining_time":26.22665124},
{"learn":[0.6910795724],"iteration":269,"passed_time":9.671408436,"remaining_time":26.14862281},
{"learn":[0.6910318301],"iteration":270,"passed_time":9.694278859,"remaining_time":26.07796785},
{"learn":[0.6909478686],"iteration":271,"passed_time":9.712940082,"remaining_time":25.99639846},
{"learn":[0.6908394016],"iteration":272,"passed_time":9.733201785,"remaining_time":25.91955201},
{"learn":[0.6907182277],"iteration":273,"passed_time":9.754383219,"remaining_time":25.84555554},
{"learn":[0.6905075059],"iteration":274,"passed_time":9.775789766,"remaining_time":25.77253666},
{"learn":[0.6903625341],"iteration":275,"passed_time":9.798943254,"remaining_time":25.70447433},
{"learn":[0.6902902743],"iteration":276,"passed_time":9.81719574,"remaining_time":25.62394411},
{"learn":[0.6895457714],"iteration":277,"passed_time":9.839494546,"remaining_time":25.55437073},
{"learn":[0.6894413311],"iteration":278,"passed_time":9.86098712,"remaining_time":25.48305274},
{"learn":[0.6892605318],"iteration":279,"passed_time":9.881876351,"remaining_time":25.41053919},
{"learn":[0.689216967],"iteration":280,"passed_time":9.906617022,"remaining_time":25.34824782},
{"learn":[0.689044165],"iteration":281,"passed_time":9.927409591,"remaining_time":25.27617052},
{"learn":[0.6889820602],"iteration":282,"passed_time":9.947281504,"remaining_time":25.2021231},
{"learn":[0.6888685355],"iteration":283,"passed_time":9.968047411,"remaining_time":25.13071108},
{"learn":[0.6886459596],"iteration":284,"passed_time":9.991707783,"remaining_time":25.06691602},
{"learn":[0.6885433772],"iteration":285,"passed_time":10.01477366,"remaining_time":25.00191746},
{"learn":[0.6884453792],"iteration":286,"passed_time":10.03478543,"remaining_time":24.92962374},
{"learn":[0.6883688359],"iteration":287,"passed_time":10.05673694,"remaining_time":24.86248854},
{"learn":[0.6883008554],"iteration":288,"passed_time":10.07820174,"remaining_time":24.79446863},
{"learn":[0.6882250966],"iteration":289,"passed_time":10.10164226,"remaining_time":24.73160692},
{"learn":[0.6881365391],"iteration":290,"passed_time":10.12231404,"remaining_time":24.6622703},
{"learn":[0.6880318169],"iteration":291,"passed_time":10.14347053,"remaining_time":24.59444224},
{"learn":[0.6878696925],"iteration":292,"passed_time":10.16391568,"remaining_time":24.52521633},
{"learn":[0.6878198453],"iteration":293,"passed_time":10.18365527,"remaining_time":24.45462795},
{"learn":[0.6877147683],"iteration":294,"passed_time":10.20817276,"remaining_time":24.39580269},
{"learn":[0.6876563464],"iteration":295,"passed_time":10.22956676,"remaining_time":24.3297804},
{"learn":[0.6875934528],"iteration":296,"passed_time":10.25081597,"remaining_time":24.26371591},
{"learn":[0.6875376826],"iteration":297,"passed_time":10.2721659,"remaining_time":24.19818946},
{"learn":[0.6875000138],"iteration":298,"passed_time":10.29397103,"remaining_time":24.13402573},
{"learn":[0.6873883973],"iteration":299,"passed_time":10.31582862,"remaining_time":24.07026678},
{"learn":[0.687285051],"iteration":300,"passed_time":10.3345176,"remaining_time":23.99942792},
{"learn":[0.687204969],"iteration":301,"passed_time":10.35624624,"remaining_time":23.93595986},
{"learn":[0.6870592487],"iteration":302,"passed_time":10.37579822,"remaining_time":23.86776025},
{"learn":[0.6869961606],"iteration":303,"passed_time":10.39584187,"remaining_time":23.80100639},
{"learn":[0.6869441515],"iteration":304,"passed_time":10.41673194,"remaining_time":23.73648754},
{"learn":[0.6868304031],"iteration":305,"passed_time":10.43811878,"remaining_time":23.67338051},
{"learn":[0.6861352853],"iteration":306,"passed_time":10.45768363,"remaining_time":23.60643242},
{"learn":[0.6860847259],"iteration":307,"passed_time":10.47975201,"remaining_time":23.54541685},
{"learn":[0.6858754191],"iteration":308,"passed_time":10.50062241,"remaining_time":23.48197438},
{"learn":[0.6858394326],"iteration":309,"passed_time":10.52189412,"remaining_time":23.41969982},
{"learn":[0.6857898294],"iteration":310,"passed_time":10.54145784,"remaining_time":23.353905},
{"learn":[0.6857435685],"iteration":311,"passed_time":10.56075273,"remaining_time":23.28781371},
{"learn":[0.6857424671],"iteration":312,"passed_time":10.57644988,"remaining_time":23.21412482},
{"learn":[0.6856614686],"iteration":313,"passed_time":10.59898478,"remaining_time":23.15574382},
{"learn":[0.6854629822],"iteration":314,"passed_time":10.62210369,"remaining_time":23.09886041},
{"learn":[0.6853305539],"iteration":315,"passed_time":10.64460882,"remaining_time":23.04086212},
{"learn":[0.6851880345],"iteration":316,"passed_time":10.66605987,"remaining_time":22.98081668},
{"learn":[0.6850848535],"iteration":317,"passed_time":10.68548044,"remaining_time":22.9166593},
{"learn":[0.6849344858],"iteration":318,"passed_time":10.70766159,"remaining_time":22.85867567},
{"learn":[0.6848950693],"iteration":319,"passed_time":10.73038881,"remaining_time":22.80207621},
{"learn":[0.6846608341],"iteration":320,"passed_time":10.75282959,"remaining_time":22.74508191},
{"learn":[0.6845807408],"iteration":321,"passed_time":10.77630215,"remaining_time":22.69047472},
{"learn":[0.6845236906],"iteration":322,"passed_time":10.79811777,"remaining_time":22.63258741},
{"learn":[0.6844468235],"iteration":323,"passed_time":10.82035955,"remaining_time":22.5758119},
{"learn":[0.6842192192],"iteration":324,"passed_time":10.84310565,"remaining_time":22.52029635},
{"learn":[0.6841326823],"iteration":325,"passed_time":10.86132333,"remaining_time":22.45561941},
{"learn":[0.6840660067],"iteration":326,"passed_time":10.8820674,"remaining_time":22.39642618},
{"learn":[0.6839613083],"iteration":327,"passed_time":10.90472682,"remaining_time":22.34139153},
{"learn":[0.6839321527],"iteration":328,"passed_time":10.9254931,"remaining_time":22.28269261},
{"learn":[0.6838555734],"iteration":329,"passed_time":10.9474911,"remaining_time":22.22672435},
{"learn":[0.6838338573],"iteration":330,"passed_time":10.96682559,"remaining_time":22.165578},
{"learn":[0.6836647825],"iteration":331,"passed_time":10.98755755,"remaining_time":22.10749531},
{"learn":[0.6836021586],"iteration":332,"passed_time":11.00689819,"remaining_time":22.04685013},
{"learn":[0.683528562],"iteration":333,"passed_time":11.02782076,"remaining_time":21.98960667},
{"learn":[0.6834413535],"iteration":334,"passed_time":11.0479872,"remaining_time":21.93107906},
{"learn":[0.6834132064],"iteration":335,"passed_time":11.06956862,"remaining_time":21.87557608},
{"learn":[0.683341242],"iteration":336,"passed_time":11.08783012,"remaining_time":21.81374294},
{"learn":[0.6832588388],"iteration":337,"passed_time":11.11004934,"remaining_time":21.75991912},
{"learn":[0.6832485409],"iteration":338,"passed_time":11.12788572,"remaining_time":21.69773588},
{"learn":[0.683135734],"iteration":339,"passed_time":11.14934782,"remaining_time":21.64285166},
{"learn":[0.6830983109],"iteration":340,"passed_time":11.17118995,"remaining_time":21.58889788},
{"learn":[0.6830325631],"iteration":341,"passed_time":11.19098147,"remaining_time":21.53118658},
{"learn":[0.6826452649],"iteration":342,"passed_time":11.21270398,"remaining_time":21.47739509},
{"learn":[0.6824501385],"iteration":343,"passed_time":11.23661053,"remaining_time":21.42795497},
{"learn":[0.6824180052],"iteration":344,"passed_time":11.25714575,"remaining_time":21.37226223},
{"learn":[0.6823476046],"iteration":345,"passed_time":11.28037583,"remaining_time":21.32186645},
{"learn":[0.682296108],"iteration":346,"passed_time":11.30183621,"remaining_time":21.26829695},
{"learn":[0.6821804869],"iteration":347,"passed_time":11.32466151,"remaining_time":21.21746927},
{"learn":[0.6815745175],"iteration":348,"passed_time":11.34440972,"remaining_time":21.16106226},
{"learn":[0.6815111503],"iteration":349,"passed_time":11.36474168,"remaining_time":21.10594884},
{"learn":[0.6813295488],"iteration":350,"passed_time":11.38660142,"remaining_time":21.05385847},
{"learn":[0.6810864693],"iteration":351,"passed_time":11.40863612,"remaining_time":21.00226195},
{"learn":[0.681007915],"iteration":352,"passed_time":11.43188915,"remaining_time":20.95306595},
{"learn":[0.6809556914],"iteration":353,"passed_time":11.45398252,"remaining_time":20.9019003},
{"learn":[0.6808874521],"iteration":354,"passed_time":11.47656628,"remaining_time":20.85178944},
{"learn":[0.6808136198],"iteration":355,"passed_time":11.49920219,"remaining_time":20.80192755},
{"learn":[0.6807595656],"iteration":356,"passed_time":11.52122665,"remaining_time":20.75111691},
{"learn":[0.6806789014],"iteration":357,"passed_time":11.54630188,"remaining_time":20.70593801},
{"learn":[0.6806418869],"iteration":358,"passed_time":11.56796297,"remaining_time":20.6547751},
{"learn":[0.6806104052],"iteration":359,"passed_time":11.58963352,"remaining_time":20.60379293},
{"learn":[0.6805540356],"iteration":360,"passed_time":11.61219103,"remaining_time":20.55454313},
{"learn":[0.6805122277],"iteration":361,"passed_time":11.63422432,"remaining_time":20.50451689},
{"learn":[0.680364959],"iteration":362,"passed_time":11.65706006,"remaining_time":20.45605306},
{"learn":[0.6799338258],"iteration":363,"passed_time":11.67695874,"remaining_time":20.40259824},
{"learn":[0.6798681337],"iteration":364,"passed_time":11.69932149,"remaining_time":20.35361411},
{"learn":[0.6798254661],"iteration":365,"passed_time":11.71914921,"remaining_time":20.30038415},
{"learn":[0.6797457882],"iteration":366,"passed_time":11.74268329,"remaining_time":20.25372895},
{"learn":[0.6796645116],"iteration":367,"passed_time":11.76769751,"remaining_time":20.20974138},
{"learn":[0.6795917731],"iteration":368,"passed_time":11.79095252,"remaining_time":20.16284834},
{"learn":[0.6795078269],"iteration":369,"passed_time":11.81005968,"remaining_time":20.10902053},
{"learn":[0.6794675296],"iteration":370,"passed_time":11.82845584,"remaining_time":20.05417446},
{"learn":[0.6793514703],"iteration":371,"passed_time":11.8520059,"remaining_time":20.00822501},
{"learn":[0.679272533],"iteration":372,"passed_time":11.87311243,"remaining_time":19.95828818},
{"learn":[0.6792201734],"iteration":373,"passed_time":11.89463189,"remaining_time":19.90919669},
{"learn":[0.6792026286],"iteration":374,"passed_time":11.91745196,"remaining_time":19.86241993},
{"learn":[0.679120815],"iteration":375,"passed_time":11.9390963,"remaining_time":19.8138194},
{"learn":[0.6787986136],"iteration":376,"passed_time":11.96278303,"remaining_time":19.76873695},
{"learn":[0.6787275017],"iteration":377,"passed_time":11.98392367,"remaining_time":19.7195781},
{"learn":[0.6787145323],"iteration":378,"passed_time":12.00175295,"remaining_time":19.66514138},
{"learn":[0.6785791573],"iteration":379,"passed_time":12.02081951,"remaining_time":19.61291604},
{"learn":[0.6784976953],"iteration":380,"passed_time":12.0420239,"remaining_time":19.56433804},
{"learn":[0.6784127339],"iteration":381,"passed_time":12.06278519,"remaining_time":19.5151865},
{"learn":[0.6783447496],"iteration":382,"passed_time":12.08081481,"remaining_time":19.4617826},
{"learn":[0.678276338],"iteration":383,"passed_time":12.10231781,"remaining_time":19.41413482},
{"learn":[0.6782096746],"iteration":384,"passed_time":12.12009881,"remaining_time":19.36067731},
{"learn":[0.6781198641],"iteration":385,"passed_time":12.14052382,"remaining_time":19.31161043},
{"learn":[0.6780268578],"iteration":386,"passed_time":12.16086526,"remaining_time":19.26255918},
{"learn":[0.67798663],"iteration":387,"passed_time":12.18177883,"remaining_time":19.21455836},
{"learn":[0.677843591],"iteration":388,"passed_time":12.2030929,"remaining_time":19.16732587},
{"learn":[0.6778055466],"iteration":389,"passed_time":12.22330055,"remaining_time":19.11849574},
{"learn":[0.677763989],"iteration":390,"passed_time":12.24587105,"remaining_time":19.07349224},
{"learn":[0.6777630182],"iteration":391,"passed_time":12.26222743,"remaining_time":19.018965},
{"learn":[0.6776203858],"iteration":392,"passed_time":12.28192026,"remaining_time":18.96978524},
{"learn":[0.6775558914],"iteration":393,"passed_time":12.30196803,"remaining_time":18.92130108},
{"learn":[0.6775136683],"iteration":394,"passed_time":12.32412996,"remaining_time":18.87619905},
{"learn":[0.6774707331],"iteration":395,"passed_time":12.34847805,"remaining_time":18.83454733},
{"learn":[0.6774459192],"iteration":396,"passed_time":12.36808436,"remaining_time":18.78578053},
{"learn":[0.6774076753],"iteration":397,"passed_time":12.38915767,"remaining_time":18.73937919},
{"learn":[0.677355508],"iteration":398,"passed_time":12.40959683,"remaining_time":18.69214961},
{"learn":[0.6772618319],"iteration":399,"passed_time":12.430868,"remaining_time":18.646302},
{"learn":[0.6772187203],"iteration":400,"passed_time":12.45110682,"remaining_time":18.59903487},
{"learn":[0.677180964],"iteration":401,"passed_time":12.46964837,"remaining_time":18.54937743},
{"learn":[0.6771409573],"iteration":402,"passed_time":12.49152063,"remaining_time":18.50480847},
{"learn":[0.6770208614],"iteration":403,"passed_time":12.51200026,"remaining_time":18.45829741},
{"learn":[0.6769669923],"iteration":404,"passed_time":12.53110821,"remaining_time":18.40989972},
{"learn":[0.676945141],"iteration":405,"passed_time":12.55239665,"remaining_time":18.36483648},
{"learn":[0.6763875251],"iteration":406,"passed_time":12.57439942,"remaining_time":18.32093085},
{"learn":[0.676386614],"iteration":407,"passed_time":12.58996442,"remaining_time":18.26779151},
{"learn":[0.6763514837],"iteration":408,"passed_time":12.60970144,"remaining_time":18.22086442},
{"learn":[0.6762318698],"iteration":409,"passed_time":12.63093015,"remaining_time":18.17621656},
{"learn":[0.67611809],"iteration":410,"passed_time":12.65208741,"remaining_time":18.13158025},
{"learn":[0.6760167208],"iteration":411,"passed_time":12.67298409,"remaining_time":18.08668604},
{"learn":[0.6760158588],"iteration":412,"passed_time":12.6888313,"remaining_time":18.03473118},
{"learn":[0.6759868074],"iteration":413,"passed_time":12.71017974,"remaining_time":17.9907375},
{"learn":[0.675921902],"iteration":414,"passed_time":12.72946837,"remaining_time":17.94394938},
{"learn":[0.6758829596],"iteration":415,"passed_time":12.74872961,"remaining_time":17.89725502},
{"learn":[0.6757745468],"iteration":416,"passed_time":12.76890347,"remaining_time":17.85196815},
{"learn":[0.6757598355],"iteration":417,"passed_time":12.78721502,"remaining_time":17.80420847},
{"learn":[0.6756418495],"iteration":418,"passed_time":12.80872081,"remaining_time":17.76101859},
{"learn":[0.6755507886],"iteration":419,"passed_time":12.82998231,"remaining_time":17.71759462},
{"learn":[0.6755504123],"iteration":420,"passed_time":12.84810706,"remaining_time":17.66996197},
{"learn":[0.6754908181],"iteration":421,"passed_time":12.86941787,"remaining_time":17.62683301},
{"learn":[0.6753420108],"iteration":422,"passed_time":12.88887562,"remaining_time":17.58127951},
{"learn":[0.6751149769],"iteration":423,"passed_time":12.90835294,"remaining_time":17.53587569},
{"learn":[0.6750524016],"iteration":424,"passed_time":12.93021361,"remaining_time":17.49381841},
{"learn":[0.67496358],"iteration":425,"passed_time":12.94947773,"remaining_time":17.44835732},
{"learn":[0.6748948739],"iteration":426,"passed_time":12.97102631,"remaining_time":17.40608448},
{"learn":[0.6748061424],"iteration":427,"passed_time":12.99400848,"remaining_time":17.36582442},
{"learn":[0.6747368405],"iteration":428,"passed_time":13.01656226,"remaining_time":17.32507471},
{"learn":[0.6746328617],"iteration":429,"passed_time":13.0378652,"remaining_time":17.28275155},
{"learn":[0.6746320493],"iteration":430,"passed_time":13.05144494,"remaining_time":17.23032987},
{"learn":[0.6745384063],"iteration":431,"passed_time":13.07528708,"remaining_time":17.19158116},
{"learn":[0.6745019431],"iteration":432,"passed_time":13.09567523,"remaining_time":17.14837842},
{"learn":[0.6745011766],"iteration":433,"passed_time":13.11195984,"remaining_time":17.09992919},
{"learn":[0.6744319216],"iteration":434,"passed_time":13.13148126,"remaining_time":17.05583198},
{"learn":[0.6742740134],"iteration":435,"passed_time":13.15486989,"remaining_time":17.01685004},
{"learn":[0.6741843252],"iteration":436,"passed_time":13.1756991,"remaining_time":16.9746421},
{"learn":[0.6741125195],"iteration":437,"passed_time":13.19833981,"remaining_time":16.9348561},
{"learn":[0.6740103943],"iteration":438,"passed_time":13.22027346,"remaining_time":16.89424468},
{"learn":[0.673885057],"iteration":439,"passed_time":13.23828379,"remaining_time":16.84872483},
{"learn":[0.6738430062],"iteration":440,"passed_time":13.25848334,"remaining_time":16.80610474},
{"learn":[0.6737609363],"iteration":441,"passed_time":13.27831802,"remaining_time":16.76312547},
{"learn":[0.6737081258],"iteration":442,"passed_time":13.29950992,"remaining_time":16.72195717},
{"learn":[0.6736565234],"iteration":443,"passed_time":13.32063021,"remaining_time":16.68078918},
{"learn":[0.6735144034],"iteration":444,"passed_time":13.33972893,"remaining_time":16.63719002},
{"learn":[0.6734324645],"iteration":445,"passed_time":13.35824783,"remaining_time":16.59298049},
{"learn":[0.6732682492],"iteration":446,"passed_time":13.38059009,"remaining_time":16.55361593},
{"learn":[0.6732369928],"iteration":447,"passed_time":13.40155338,"remaining_time":16.51262828},
{"learn":[0.6727180253],"iteration":448,"passed_time":13.42409621,"remaining_time":16.47366818},
{"learn":[0.6726664898],"iteration":449,"passed_time":13.44459496,"remaining_time":16.43228273},
{"learn":[0.6726367493],"iteration":450,"passed_time":13.46665502,"remaining_time":16.39289048},
{"learn":[0.6725431972],"iteration":451,"passed_time":13.48896972,"remaining_time":16.35388365},
{"learn":[0.6724142909],"iteration":452,"passed_time":13.51274519,"remaining_time":16.31671439},
{"learn":[0.6723943595],"iteration":453,"passed_time":13.53311601,"remaining_time":16.27550956},
{"learn":[0.6723767754],"iteration":454,"passed_time":13.55194098,"remaining_time":16.23254469},
{"learn":[0.6723439435],"iteration":455,"passed_time":13.5701093,"remaining_time":16.18890233},
{"learn":[0.6722582245],"iteration":456,"passed_time":13.59398347,"remaining_time":16.15215103},
{"learn":[0.6721358194],"iteration":457,"passed_time":13.61567102,"remaining_time":16.11286832},
{"learn":[0.6720464438],"iteration":458,"passed_time":13.63956692,"remaining_time":16.07626515},
{"learn":[0.6719787317],"iteration":459,"passed_time":13.66246522,"remaining_time":16.03854613},
{"learn":[0.6719551804],"iteration":460,"passed_time":13.6828107,"remaining_time":15.99790665},
{"learn":[0.671869334],"iteration":461,"passed_time":13.70284873,"remaining_time":15.956997},
{"learn":[0.6718689539],"iteration":462,"passed_time":13.71804577,"remaining_time":15.9105628},
{"learn":[0.671800367],"iteration":463,"passed_time":13.7387162,"remaining_time":15.87058596},
{"learn":[0.6716969698],"iteration":464,"passed_time":13.7598314,"remaining_time":15.83120387},
{"learn":[0.6716557011],"iteration":465,"passed_time":13.77940467,"remaining_time":15.79013325},
{"learn":[0.6715572748],"iteration":466,"passed_time":13.80215571,"remaining_time":15.75278157},
{"learn":[0.6714705825],"iteration":467,"passed_time":13.8285161,"remaining_time":15.71959523},
{"learn":[0.671333426],"iteration":468,"passed_time":13.84769847,"remaining_time":15.67831106},
{"learn":[0.6711885909],"iteration":469,"passed_time":13.87109355,"remaining_time":15.64187145},
{"learn":[0.6710599524],"iteration":470,"passed_time":13.89031718,"remaining_time":15.6008021},
{"learn":[0.6710141736],"iteration":471,"passed_time":13.91275291,"remaining_time":15.56341851},
{"learn":[0.6710138706],"iteration":472,"passed_time":13.92714364,"remaining_time":15.51713467},
{"learn":[0.670892557],"iteration":473,"passed_time":13.94650759,"remaining_time":15.4765042},
{"learn":[0.670829422],"iteration":474,"passed_time":13.96683467,"remaining_time":15.4370278},
{"learn":[0.6707768823],"iteration":475,"passed_time":13.98804471,"remaining_time":15.39860384},
{"learn":[0.6707244097],"iteration":476,"passed_time":14.01004083,"remaining_time":15.36111395},
{"learn":[0.6703694534],"iteration":477,"passed_time":14.03077062,"remaining_time":15.32230599},
{"learn":[0.6702657742],"iteration":478,"passed_time":14.051795,"remaining_time":15.28389394},
{"learn":[0.6702194578],"iteration":479,"passed_time":14.07330372,"remaining_time":15.24607903},
{"learn":[0.6702028241],"iteration":480,"passed_time":14.09455447,"remaining_time":15.20805358},
{"learn":[0.6701161187],"iteration":481,"passed_time":14.11534508,"remaining_time":15.16960322},
{"learn":[0.6697590945],"iteration":482,"passed_time":14.13564957,"remaining_time":15.13070565},
{"learn":[0.669744805],"iteration":483,"passed_time":14.15491126,"remaining_time":15.09077316},
{"learn":[0.6696747655],"iteration":484,"passed_time":14.17663978,"remaining_time":15.05354533},
{"learn":[0.6696166499],"iteration":485,"passed_time":14.19746929,"remaining_time":15.01543048},
{"learn":[0.6695032438],"iteration":486,"passed_time":14.21741447,"remaining_time":14.97645507},
{"learn":[0.669453401],"iteration":487,"passed_time":14.23902587,"remaining_time":14.93930583},
{"learn":[0.6692379414],"iteration":488,"passed_time":14.26096693,"remaining_time":14.90256463},
{"learn":[0.6691311428],"iteration":489,"passed_time":14.28253274,"remaining_time":14.86549326},
{"learn":[0.6690435342],"iteration":490,"passed_time":14.2996319,"remaining_time":14.82385466},
{"learn":[0.6687601193],"iteration":491,"passed_time":14.315377,"remaining_time":14.78091771},
{"learn":[0.6686798693],"iteration":492,"passed_time":14.33989118,"remaining_time":14.74710918},
{"learn":[0.6685878471],"iteration":493,"passed_time":14.36560485,"remaining_time":14.71456691},
{"learn":[0.6685337028],"iteration":494,"passed_time":14.38703512,"remaining_time":14.67768229},
{"learn":[0.6685132498],"iteration":495,"passed_time":14.4098372,"remaining_time":14.64225393},
{"learn":[0.6684330696],"iteration":496,"passed_time":14.43229714,"remaining_time":14.6065301},
{"learn":[0.6684124499],"iteration":497,"passed_time":14.45094295,"remaining_time":14.56701478},
{"learn":[0.668393492],"iteration":498,"passed_time":14.47598891,"remaining_time":14.53400891},
{"learn":[0.6683305508],"iteration":499,"passed_time":14.49887479,"remaining_time":14.49887479},
{"learn":[0.6682781417],"iteration":500,"passed_time":14.51897387,"remaining_time":14.46101389},
{"learn":[0.6682199995],"iteration":501,"passed_time":14.54372482,"remaining_time":14.42783857},
{"learn":[0.6681792632],"iteration":502,"passed_time":14.56486606,"remaining_time":14.39113008},
{"learn":[0.668178593],"iteration":503,"passed_time":14.57868554,"remaining_time":14.34727783},
{"learn":[0.6681305064],"iteration":504,"passed_time":14.59653628,"remaining_time":14.30749596},
{"learn":[0.668080243],"iteration":505,"passed_time":14.61386696,"remaining_time":14.26729304},
{"learn":[0.6680796054],"iteration":506,"pa,
{"learn":[0.6818710157],"iteration":506,"passed_ti,
{"learn":[0.6680789852],"iteration":507,"pa,
{"learn":[0.6817887319],"iteration":507,"passed_t,
{"learn":[0.6680259456],"iteration":508,"pas,
{"learn":[0.6817581977],"iteration":508,"passed_t,
{"learn":[0.667959179],"iteration":509,"pass,
{"learn":[0.6817095797],"iteration":509,"passed_,
{"learn":[0.6679249958],"iteration":510,"pass,
{"learn":[0.6816686246],"iteration":510,"passed_,
{"learn":[0.667896841],"iteration":511,"passe,
{"learn":[0.6816230386],"iteration":511,"passed,
{"learn":[0.6678307982],"iteration":512,"passe,
{"learn":[0.6815632789],"iteration":512,"passe,
{"learn":[0.6678008881],"iteration":513,"passed,
{"learn":[0.6815097543],"iteration":513,"passe,
{"learn":[0.66780031],"iteration":514,"passed_t,
{"learn":[0.6814941761],"iteration":514,"pas,
{"learn":[0.667773552],"iteration":515,"passed_ti,
{"learn":[0.6814235504],"iteration":515,"pa,
{"learn":[0.6677316637],"iteration":516,"passed_t,
{"learn":[0.6813711631],"iteration":516,"pa,
{"learn":[0.6676707228],"iteration":517,"passed_ti,
{"learn":[0.6812557653],"iteration":517,"pa,
{"learn":[0.6676335523],"iteration":518,"passed_ti,
{"learn":[0.6812305438],"iteration":518,"passed_time":14.95187309,"remaining_time":13.85713093},
{"learn":[0.6812131834],"iteration":519,"passed_time":14.97181307,"remaining_time":13.82013514},
{"learn":[0.6811830805],"iteration":520,"passed_time":14.99558403,"remaining_time":13.78672697},
{"learn":[0.6811707372],"iteration":521,"pa,
{"learn":[0.667444551],"iteration":522,"passed_ti,
{"learn":[0.6810978483],"iteration":522,"passed_time":15.03888541,"remaining_time":13.71615361},
{"learn":[0.6810404816],"iteration":523,"pa,
{"learn":[0.6672455597],"iteration":524,"passed_ti,
{"learn":[0.6809701084],"iteration":524,"passed_time":15.08079087,"remaining_time":13.64452507},
{"learn":[0.6807701405],"iteration":525,"passed_time":15.10520886,"remaining_time":13.61191825},
{"learn":[0.6807525539],"iteration":526,"passed_time":15.12497285,"remaining_time":13.57516539},
{"learn":[0.6806564943],"iteration":527,"passed_time":15.14760124,"remaining_time":13.54103747},
{"learn":[0.6803934577],"iteration":528,"passed_time":15.17438018,"remaining_time":13.51064851},
{"learn":[0.6803010491],"iteration":529,"passed_time":15.20012021,"remaining_time":13.47935188},
{"learn":[0.6802833414],"iteration":530,"passed_time":15.21868607,"remaining_time":13.44173968},
{"learn":[0.6802247387],"iteration":531,"passed_time":15.2419647,"remaining_time":13.40834488},
{"learn":[0.6801911956],"iteration":532,"passed_time":15.26476483,"remaining_time":13.37456881},
{"learn":[0.6801837795],"iteration":533,"passed_time":15.28415042,"remaining_time":13.33785411},
{"learn":[0.6800539406],"iteration":534,"passed_time":15.30485705,"remaining_time":13.30235239},
{"learn":[0.6800430745],"iteration":535,"passed_time":15.32351998,"remaining_time":13.2651367},
{"learn":[0.6799718519],"iteration":536,"passed_time":15.3444946,"remaining_time":13.22998324},
{"learn":[0.6799236474],"iteration":537,"passed_time":15.36442705,"remaining_time":13.19398754},
{"learn":[0.679754485],"iteration":538,"passed_time":15.38601247,"remaining_time":13.15946521},
{"learn":[0.6796939161],"iteration":539,"passed_time":15.40824019,"remaining_time":13.12553794},
{"learn":[0.6796488238],"iteration":540,"passed_time":15.42772365,"remaining_time":13.08932561},
{"learn":[0.6795610459],"iteration":541,"passed_time":15.44855069,"remaining_time":13.05431036},
{"learn":[0.6794728632],"iteration":542,"passed_time":15.47035591,"remaining_time":13.02017063},
{"learn":[0.6794439219],"iteration":543,"passed_time":15.49386689,"remaining_time":12.98750607},
{"learn":[0.6793999646],"iteration":544,"passed_time":15.51579147,"remaining_time":12.95355068},
{"learn":[0.6793705244],"iteration":545,"passed_time":15.53783968,"remaining_time":12.91974215},
{"learn":[0.679250487],"iteration":546,"passed_time":15.5589466,"remaining_time":12.88519709},
{"learn":[0.6792141094],"iteration":547,"passed_time":15.57941285,"remaining_time":12.85017264},
{"learn":[0.6791502345],"iteration":548,"passed_time":15.59942872,"remaining_time":12.81483125},
{"learn":[0.679033848],"iteration":549,"passed_time":15.61925927,"remaining_time":12.77939395},
{"learn":[0.679013794],"iteration":550,"passed_time":15.64017405,"remaining_time":12.74489682},
{"learn":[0.6789785864],"iteration":551,"passed_time":15.65926706,"remaining_time":12.70897037},
{"learn":[0.6789473119],"iteration":552,"passed_time":15.68267392,"remaining_time":12.67659176},
{"learn":[0.6789270943],"iteration":553,"passed_time":15.70206474,"remaining_time":12.64101241},
{"learn":[0.6787046986],"iteration":554,"passed_time":15.72509451,"remaining_time":12.60840911},
{"learn":[0.6786522599],"iteration":555,"passed_time":15.74653177,"remaining_time":12.57456854},
{"learn":[0.6785942481],"iteration":556,"passed_time":15.77123782,"remaining_time":12.54337227},
{"learn":[0.6785505255],"iteration":557,"passed_time":15.79407237,"remaining_time":12.51071682},
{"learn":[0.6784682725],"iteration":558,"passed_time":15.82016713,"remaining_time":12.48066852},
{"learn":[0.6783916238],"iteration":559,"passed_time":15.84298925,"remaining_time":12.44806298},
{"learn":[0.6783404668],"iteration":560,"passed_time":15.86434505,"remaining_time":12.41434488},
{"learn":[0.6783072236],"iteration":561,"passed_time":15.88506207,"remaining_time":12.38017293},
{"learn":[0.6782257772],"iteration":562,"passed_time":15.90583716,"remaining_time":12.34609385},
{"learn":[0.6781864642],"iteration":563,"passed_time":15.9306126,"remaining_time":12.31515442},
{"learn":[0.6781627766],"iteration":564,"passed_time":15.95249122,"remaining_time":12.28200652},
{"learn":[0.6781340942],"iteration":565,"passed_time":15.97219396,"remaining_time":12.24723},
{"learn":[0.6780945913],"iteration":566,"passed_time":15.99661547,"remaining_time":12.21611023},
{"learn":[0.6780825385],"iteration":567,"passed_time":16.01690648,"remaining_time":12.18187254},
{"learn":[0.6778924544],"iteration":568,"passed_time":16.04010659,"remaining_time":12.14988742},
{"learn":[0.6778627191],"iteration":569,"passed_time":16.06252417,"remaining_time":12.11734279},
{"learn":[0.6777399346],"iteration":570,"passed_time":16.08752552,"remaining_time":12.08677486},
{"learn":[0.6776522181],"iteration":571,"passed_time":16.11227973,"remaining_time":12.05604147},
{"learn":[0.6775768239],"iteration":572,"passed_time":16.13464274,"remaining_time":12.02354703},
{"learn":[0.6775535413],"iteration":573,"passed_time":16.15769461,"remaining_time":11.99159913},
{"learn":[0.6775175752],"iteration":574,"passed_time":16.18356203,"remaining_time":11.96176324},
{"learn":[0.6775037773],"iteration":575,"passed_time":16.20525169,"remaining_time":11.92886583},
{"learn":[0.6774377377],"iteration":576,"passed_time":16.23010281,"remaining_time":11.89832493},
{"learn":[0.677394867],"iteration":577,"passed_time":16.25463098,"remaining_time":11.86756795},
{"learn":[0.6773645429],"iteration":578,"passed_time":16.27380055,"remaining_time":11.83293615},
{"learn":[0.6773280537],"iteration":579,"passed_time":16.29880315,"remaining_time":11.80258159},
{"learn":[0.6773211307],"iteration":580,"passed_time":16.31998868,"remaining_time":11.7694927},
{"learn":[0.6772526985],"iteration":581,"passed_time":16.34364459,"remaining_time":11.73821897},
{"learn":[0.6772043857],"iteration":582,"passed_time":16.36757634,"remaining_time":11.70716867},
{"learn":[0.6771605212],"iteration":583,"passed_time":16.38607839,"remaining_time":11.67227502},
{"learn":[0.6771380104],"iterati,
{"learn":[0.664002527],"iteration":585,"passed_time":16.3582,
{"learn":[0.6771058453],"iterati,
{"learn":[0.6639248461],"iteration":586,"passed_time":16.38,
{"learn":[0.6770085289],"iteration,
{"learn":[0.6638846522],"iteration":587,"passed_time":16.40,
{"learn":[0.6769219767],"iteratio,
{"learn":[0.6638598359],"iteration":588,"passed_time":16.42,
{"learn":[0.6768636352],"iteration,
{"learn":[0.6637820174],"iteration":589,"passed_time":16.45,
{"learn":[0.6768015842],"iteration,
{"learn":[0.6637597011],"iteration":590,"passed_time":16.4,
{"learn":[0.6767761023],"iteration",
{"learn":[0.6637087337],"iteration":591,"passed_time":16.4,
{"learn":[0.6767617465],"iteration,
{"learn":[0.6636924628],"iteration":592,"passed_time":16.51,
{"learn":[0.6767076685],"iteration,
{"learn":[0.66368797],"iteration":593,"passed_time":16.529,
{"learn":[0.6766680881],"iteration":593,"passed_time":16.60855018,"remaining_time":11.35197201},
{"learn":[0.6766316749],"iteration":594,"passed_time":16.63091821,"remaining_time":11.32020483},
{"learn":[0.6766108046],"iteration":595,"passed_time":16.6510886,"remaining_time":11.28697952},
{"learn":[0.6765782294],"iteration":596,"passed_time":16.67185876,"remaining_time":11.25420282},
{"learn":[0.6765047048],"iteration":597,"passed_time":16.6945303,"remaining_time":11.22274445},
{"learn":[0.6764769291],"iteration":598,"passed_time":16.71629192,"remaining_time":11.19070627},
{"learn":[0.6764367799],"iteration":599,"passed_time":16.74128379,"remaining_time":11.16085586},
{"learn":[0.6764135806],"iteration":600,"passed_time":16.7636683,"remaining_time":11.1292906},
{"learn":[0.6763045874],"iteration":601,"passed_time":16.78616856,"remaining_time":11.09783237},
{"learn":[0.6760785552],"iteration":602,"passed_time":16.80530342,"remaining_time":11.06418816},
{"learn":[0.6760218776],"iteration":603,"passed_time":16.83427513,"remaining_time":11.03704131},
{"learn":[0.675976432],"iteration":604,"passed_time":16.85735193,"remaining_time":11.00603969},
{"learn":[0.67595067],"iteration":605,"passed_time":16.87848774,"remaining_time":10.97380226},
{"learn":[0.6758880808],"iteration":606,"passed_time":16.90280487,"remaining_time":10.94366114},
{"learn":[0.6758376203],"iteration":607,"passed_time":16.92658997,"remaining_time":10.91319616},
{"learn":[0.6758114851],"iteration":608,"passed_time":16.94862828,"remaining_time":10.88163162},
{"learn":[0.6757791622],"iteration":609,"passed_time":16.97213156,"remaining_time":10.85103493},
{"learn":[0.6757243118],"iteration":610,"passed_time":16.99490729,"remaining_time":10.81999826},
{"learn":[0.6756908902],"iteration":611,"passed_time":17.01370661,"remaining_time":10.78646759},
{"learn":[0.6756617728],"iteration":612,"passed_time":17.03479576,"remaining_time":10.7544306},
{"learn":[0.6754771619],"iteration":613,"passed_time":17.05539641,"remaining_time":10.72212218},
{"learn":[0.675460769],"iteration":614,"passed_time":17.07428416,"remaining_time":10.68877952},
{"learn":[0.675352646],"iteration":615,"passed_time":17.09535728,"remaining_time":10.6568461},
{"learn":[0.6752588796],"iteration":616,"passed_time":17.1168391,"remaining_time":10.62520158},
{"learn":[0.6752360756],"iteration":617,"passed_time":17.13644061,"remaining_time":10.59242769},
{"learn":[0.6751509902],"iteration":618,"passed_time":17.1569063,"remaining_time":10.56022827},
{"learn":[0.6750488288],"iteration":619,"passed_time":17.18114172,"remaining_time":10.53037718},
{"learn":[0.6750014398],"iteration":620,"passed_time":17.20387436,"remaining_time":10.49962703},
{"learn":[0.6749609782],"iteration":621,"passed_time":17.22609827,"remaining_time":10.46859348},
{"learn":[0.6749148376],"iteration":622,"passed_time":17.25117766,"remaining_time":10.43931618},
{"learn":[0.674872562],"iteration":623,"passed_time":17.27260675,"remaining_time":10.40785279},
{"learn":[0.6748583675],"iteration":624,"passed_time":17.29908178,"remaining_time":10.37944907},
{"learn":[0.6748458622],"iteration":625,"passed_time":17.32590567,"remaining_time":10.35125994},
{"learn":[0.6748061223],"iteration":626,"passed_time":17.34873104,"remaining_time":10.32069646},
{"learn":[0.6746557185],"iteration":627,"passed_time":17.37177907,"remaining_time":10.29028951},
{"learn":[0.6746349019],"iteration":628,"passed_time":17.39410882,"remaining_time":10.25948231},
{"learn":[0.6745637834],"iteration":629,"passed_time":17.4158,"remaining_time":10.22832698},
{"learn":[0.6745072653],"iteration":630,"passed_time":17.43992259,"remaining_time":10.19862351},
{"learn":[0.674335631],"iteration":631,"passed_time":17.46558102,"remaining_time":10.16983198},
{"learn":[0.6743259135],"iteration":632,"passed_time":17.48281234,"remaining_time":10.1361645},
{"learn":[0.6742850735],"iteration":633,"passed_time":17.50260829,"remaining_time":10.10402939},
{"learn":[0.6742294825],"iteration":634,"passed_time":17.52375853,"remaining_time":10.0727116},
{"learn":[0.6742034887],"iteration":635,"passed_time":17.54634455,"remaining_time":10.04224751},
{"learn":[0.6741924643],"iteration":636,"passed_time":17.56667252,"remaining_time":10.01052139},
{"learn":[0.6741347177],"iteration":637,"passed_time":17.58972683,"remaining_time":9.980377921},
{"learn":[0.6741315643],"iteration":638,"passed_time":17.60690295,"remaining_time":9.946935785},
{"learn":[0.6741073769],"iteration":639,"passed_time":17.62604548,"remaining_time":9.914650585},
{"learn":[0.673910022],"iteration":640,"passed_time":17.6502697,"remaining_time":9.885252451},
{"learn":[0.6738953115],"iteration":641,"passed_time":17.67535595,"remaining_time":9.856351139},
{"learn":[0.673850484],"iteration":642,"passed_time":17.69682053,"remaining_time":9.825450901},
{"learn":[0.673786275],"iteration":643,"passed_time":17.71527104,"remaining_time":9.792913805},
{"learn":[0.6737430206],"iteration":644,"passed_time":17.73635237,"remaining_time":9.761868359},
{"learn":[0.6736659026],"iteration":645,"passed_time":17.76253417,"remaining_time":9.733648754},
{"learn":[0.673652139],"iteration":646,"passed_time":17.78363721,"remaining_time":9.702664504},
{"learn":[0.6735955169],"iteration":647,"passed_time":17.80441636,"remaining_time":9.671534814},
{"learn":[0.6733381389],"iteration":648,"passed_time":17.82493274,"remaining_time":9.640294905},
{"learn":[0.6733204222],"iteration":649,"passed_time":17.84341339,"remaining_time":9.607991823},
{"learn":[0.6732688062],"iteration":650,"passed_time":17.86557875,"remaining_time":9.577706581},
{"learn":[0.6731958256],"iteration":651,"passed_time":17.88942339,"remaining_time":9.548342545},
{"learn":[0.673172656],"iteration":652,"passed_time":17.90778097,"remaining_time":9.516079627},
{"learn":[0.6731184786],"iteration":653,"passed_time":17.93123817,"remaining_time":9.486557199},
{"learn":[0.6728589337],"iteration":654,"passed_time":17.94976426,"remaining_time":9.454455985},
{"learn":[0.6727535917],"iteration":655,"passed_time":17.97100208,"remaining_time":9.423818162},
{"learn":[0.6726731557],"iteration":656,"passed_time":17.99315664,"remaining_time":9.393687562},
{"learn":[0.6726489791],"iteration":657,"passed_time":18.01441876,"remaining_time":9.363117348},
{"learn":[0.6725724983],"iteration":658,"passed_time":18.03662533,"remaining_time":9.333064093},
{"learn":[0.6725197919],"iteration":659,"passed_time":18.05706212,"remaining_time":9.30212291},
{"learn":[0.6724724851],"iteration":660,"passed_time":18.0789058,"remaining_time":9.271935049},
{"learn":[0.6724461712],"iteration":661,"passed_time":18.10056553,"remaining_time":9.241678473},
{"learn":[0.6724207391],"iteration":662,"passed_time":18.12214362,"remaining_time":9.211406333},
{"learn":[0.6723959805],"iteration":663,"passed_time":18.14122949,"remaining_time":9.179899259},
{"learn":[0.6723717816],"iteration":664,"passed_time":18.16378727,"remaining_time":9.150178547},
{"learn":[0.6723511834],"iteration":665,"passed_time":18.18491051,"remaining_time":9.119759926},
{"learn":[0.6723330598],"iteration":666,"passed_time":18.20773726,"remaining_time":9.090219652},
{"learn":[0.6723214286],"iteration":667,"passed_time":18.22571051,"remaining_time":9.058287261},
{"learn":[0.6722490176],"iteration":668,"passed_time":18.24685564,"remaining_time":9.027965945},
{"learn":[0.6720634784],"iteration":669,"passed_time":18.26527178,"remaining_time":8.996327894},
{"learn":[0.6719951027],"iteration":670,"passed_time":18.28999079,"remaining_time":8.967819629},
{"learn":[0.671990561],"iteration":671,"passed_time":18.30941737,"remaining_time":8.936739428},
{"learn":[0.6719701444],"iteration":672,"passed_time":18.32979385,"remaining_time":8.906155407},
{"learn":[0.6718919042],"iteration":673,"passed_time":18.35177024,"remaining_time":8.876375515},
{"learn":[0.6718578889],"iteration":674,"passed_time":18.37190926,"remaining_time":8.845734086},
{"learn":[0.6717497109],"iteration":675,"passed_time":18.39200954,"remaining_time":8.815105165},
{"learn":[0.6717328824],"iteration":676,"passed_time":18.41079699,"remaining_time":8.783880989},
{"learn":[0.6717029472],"iteration":677,"passed_time":18.43149954,"remaining_time":8.753603027},
{"learn":[0.671638597],"iteration":678,"passed_time":18.45346923,"remaining_time":8.723952318},
{"learn":[0.6716217028],"iteration":679,"passed_time":18.47433942,"remaining_time":8.693806785},
{"learn":[0.6715973321],"iteration":680,"passed_time":18.49787774,"remaining_time":8.664938326},
{"learn":[0.6715599018],"iteration":681,"passed_time":18.52675332,"remaining_time":8.638574126},
{"learn":[0.6714721144],"iteration":682,"passed_time":18.55576059,"remaining_time":8.612263701},
{"learn":[0.67145544],"iteration":683,"passed_time":18.57642818,"remaining_time":8.582092551},
{"learn":[0.6714370302],"iteration":684,"passed_time":18.59999914,"remaining_time":8.553284277},
{"learn":[0.6712870062],"iteration":685,"passed_time":18.62313318,"remaining_time":8.52429128},
{"learn":[0.6712083594],"iteration":686,"passed_time":18.64664636,"remaining_time":8.495488079},
{"learn":[0.6711014052],"iteration":687,"passed_time":18.66699694,"remaining_time":8.465266054},
{"learn":[0.6710774387],"iteration":688,"passed_time":18.69091536,"remaining_time":8.43668313},
{"learn":[0.6710208881],"iteration":689,"passed_time":18.71108265,"remaining_time":8.406428437},
{"learn":[0.6709968651],"iteration":690,"passed_time":18.73117172,"remaining_time":8.37616796},
{"learn":[0.6709689091],"iteration":691,"passed_time":18.75612024,"remaining_time":8.34809976},
{"learn":[0.6709135581],"iteration":692,"passed_time":18.77802022,"remaining_time":8.318690054},
{"learn":[0.6708894792],"iteration":693,"passed_time":18.79670709,"remaining_time":8.28788526},
{"learn":[0.6707032065],"iteration":694,"passed_time":18.81576292,"remaining_time":8.257277252},
{"learn":[0.6705378206],"iteration":695,"passed_time":18.83699235,"remaining_time":8.22765183},
{"learn":[0.6705179654],"iteration":696,"passed_time":18.85805162,"remaining_time":8.197976531},
{"learn":[0.6704164365],"iteration":697,"passed_time":18.88142488,"remaining_time":8.169327097},
{"learn":[0.6703448547],"iteration":698,"passed_time":18.90299661,"remaining_time":8.139916994},
{"learn":[0.67032473],"iteration":699,"passed_time":18.92402795,"remaining_time":8.110297692},
{"learn":[0.6702733996],"iteration":700,"passed_time":18.94562583,"remaining_time":8.080944542},
{"learn":[0.67027045],"iteration":701,"passed_time":18.96482649,"remaining_time":8.050595861},
{"learn":[0.6702464456],"iteration":702,"passed_time":18.9863997,"remaining_time":8.02128124},
{"learn":[0.6701835453],"iteration":703,"passed_time":19.0126651,"remaining_time":7.993961462},
{"learn":[0.6701318844],"iteration":704,"passed_time":19.03391689,"remaining_time":7.964546785},
{"learn":[0.6700365594],"iteration":705,"passed_time":19.05546614,"remaining_time":7.935279101},
{"learn":[0.670004872],"iteration":706,"passed_time":19.07665623,"remaining_time":7.905884405},
{"learn":[0.6699747875],"iteration":707,"passed_time":19.09643924,"remaining_time":7.875932568},
{"learn":[0.6699524592],"iteration":708,"passed_time":19.11940394,"remaining_time":7.8473153},
{"learn":[0.6695836799],"iteration":709,"passed_time":19.1388491,"remaining_time":7.817276394},
{"learn":[0.6694965268],"iteration":710,"passed_time":19.15860349,"remaining_time":7.787392982},
{"learn":[0.6694872177],"iteration":711,"passed_time":19.18065726,"remaining_time":7.758468105},
{"learn":[0.6694734009],"iteration":712,"passed_time":19.20095784,"remaining_time":7.728856804},
{"learn":[0.6694410029],"iteration":713,"passed_time":19.22345374,"remaining_time":7.700150937},
{"learn":[0.6694023351],"iteration":714,"passed_time":19.24517626,"remaining_time":7.671154175},
{"learn":[0.6693263029],"iteration":715,"passed_time":19.26899944,"remaining_time":7.64301095},
{"learn":[0.6692765724],"iteration":716,"passed_time":19.2902274,"remaining_time":7.613855447},
{"learn":[0.6692444245],"iteration":717,"passed_time":19.3118115,"remaining_time":7.584861897},
{"learn":[0.6692014698],"iteration":718,"passed_time":19.33715304,"remaining_time":7.557357448},
{"learn":[0.6691035488],"iteration":719,"passed_time":19.35828843,"remaining_time":7.52822328},
{"learn":[0.6691003477],"iteration":720,"passed_time":19.37490277,"remaining_time":7.497361819},
{"learn":[0.6690890208],"iteration":721,"passed_time":19.39491094,"remaining_time":7.467846593},
{"learn":[0.6690839239],"iteration":722,"passed_time":19.41284389,"remaining_time":7.437562596},
{"learn":[0.6690492117],"iteration":723,"passed_time":19.43541243,"remaining_time":7.409079875},
{"learn":[0.6688917194],"iteration":724,"passed_time":19.45582269,"remaining_time":7.379794815},
{"learn":[0.6688209107],"iteration":725,"passed_time":19.47840088,"remaining_time":7.351352398},
{"learn":[0.66856654],"iteration":726,"passed_time":19.50021888,"remaining_time":7.322640653},
{"learn":[0.6685402968],"iteration":727,"passed_time":19.52099647,"remaining_time":7.293559121},
{"learn":[0.6685287904],"iteration":728,"passed_time":19.53953014,"remaining_time":7.26366621},
{"learn":[0.6685107464],"iteration":729,"passed_time":19.5624284,"remaining_time":7.235418722},
{"learn":[0.668485339],"iteration":730,"passed_time":19.58416374,"remaining_time":7.206757928},
{"learn":[0.6684817188],"iteration":731,"passed_time":19.60360215,"remaining_time":7.177275105},
{"learn":[0.6682767349],"iteration":732,"passed_time":19.62640778,"remaining_time":7.149046217},
{"learn":[0.6682398179],"iteration":733,"passed_time":19.6466998,"remaining_time":7.119921181},
{"learn":[0.6681928526],"iteration":734,"passed_time":19.66444782,"remaining_time":7.089902955},
{"learn":[0.6681656141],"iteration":735,"passed_time":19.68467407,"remaining_time":7.060807005},
{"learn":[0.6679951688],"iteration":736,"passed_time":19.70617413,"remaining_time":7.032189682},
{"learn":[0.6679625342],"iteration":737,"passed_time":19.72816114,"remaining_time":7.003764522},
{"learn":[0.6678633099],"iteration":738,"passed_time":19.74625042,"remaining_time":6.973980188},
{"learn":[0.6678387637],"iteration":739,"passed_time":19.76794898,"remaining_time":6.945495588},
{"learn":[0.6678151708],"iteration":740,"passed_time":19.78911883,"remaining_time":6.916844502},
{"learn":[0.6677828956],"iteration":741,"passed_time":19.81185805,"remaining_time":6.888759266},
{"learn":[0.6677116703],"iteration":742,"passed_time":19.83329,"remaining_time":6.860236246},
{"learn":[0.6676782597],"iteration":743,"passed_time":19.85436536,"remaining_time":6.831609588},
{"learn":[0.6676393972],"iteration":744,"passed_time":19.87589355,"remaining_time":6.803158194},
{"learn":[0.6675892136],"iteration":745,"passed_time":19.89220582,"remaining_time":6.772949435},
{"learn":[0.6675811629],"iteration":746,"passed_time":19.91124143,"remaining_time":6.743700244},
{"learn":[0.6675615285],"iteration":747,"passed_time":19.93230802,"remaining_time":6.715162594},
{"learn":[0.6675550069],"iteration":748,"passed_time":19.95192745,"remaining_time":6.686159932},
{"learn":[0.6675396241],"iteration":749,"passed_time":19.97065825,"remaining_time":6.656886085},
{"learn":[0.6674256323],"iteration":750,"passed_time":19.99164911,"remaining_time":6.628389652},
{"learn":[0.6673946994],"iteration":751,"passed_time":20.0151754,"remaining_time":6.600749336},
{"learn":[0.6673648233],"iteration":752,"passed_time":20.03573387,"remaining_time":6.572146437},
{"learn":[0.6673206966],"iteration":753,"passed_time":20.05764458,"remaining_time":6.544006056},
{"learn":[0.6672786613],"iteration":754,"passed_time":20.07810722,"remaining_time":6.515412278},
{"learn":[0.6672639073],"iteration":755,"passed_time":20.10133749,"remaining_time":6.487733264},
{"learn":[0.6671932123],"iteration":756,"passed_time":20.1225381,"remaining_time":6.459414476},
{"learn":[0.6671731403],"iteration":757,"passed_time":20.14394836,"remaining_time":6.431181404},
{"learn":[0.6671024197],"iteration":758,"passed_time":20.16451956,"remaining_time":6.402699886},
{"learn":[0.667061582],"iteration":759,"passed_time":20.18604206,"remaining_time":6.374539597},
{"learn":[0.6670560186],"iteration":760,"passed_time":20.20778566,"remaining_time":6.346466193},
{"learn":[0.6670256871],"iteration":761,"passed_time":20.23019836,"remaining_time":6.318618385},
{"learn":[0.6669822626],"iteration":762,"passed_time":20.25046497,"remaining_time":6.290118216},
{"learn":[0.6669357198],"iteration":763,"passed_time":20.27647982,"remaining_time":6.263415232},
{"learn":[0.6668962166],"iteration":764,"passed_time":20.29675624,"remaining_time":6.234951263},
{"learn":[0.6667586314],"iteration":765,"passed_time":20.31978281,"remaining_time":6.207348796},
{"learn":[0.6667411032],"iteration":766,"passed_time":20.34194367,"remaining_time":6.179495275},
{"learn":[0.6666950415],"iteration":767,"passed_time":20.36606108,"remaining_time":6.152247617},
{"learn":[0.6666676604],"iteration":768,"passed_time":20.38809611,"remaining_time":6.124382577},
{"learn":[0.666660241],"iteration":769,"passed_time":20.40726252,"remaining_time":6.095675819},
{"learn":[0.6666423657],"iteration":770,"passed_time":20.42941227,"remaining_time":6.067879909},
{"learn":[0.6666168212],"iteration":771,"passed_time":20.44999318,"remaining_time":6.039635293},
{"learn":[0.6665833797],"iteration":772,"passed_time":20.47137846,"remaining_time":6.011646714},
{"learn":[0.6665589983],"iteration":773,"passed_time":20.49160264,"remaining_time":5.98333617},
{"learn":[0.6664816493],"iteration":774,"passed_time":20.51161155,"remaining_time":5.954983999},
{"learn":[0.666434434],"iteration":775,"passed_time":20.53317371,"remaining_time":5.927101689},
{"learn":[0.6663920501],"iteration":776,"passed_time":20.55604371,"remaining_time":5.899611001},
{"learn":[0.66638819],"iteration":777,"passed_time":20.57432215,"remaining_time":5.870822002},
{"learn":[0.6663841248],"iteration":778,"passed_time":20.59180918,"remaining_time":5.841835466},
{"learn":[0.6663443708],"iteration":779,"passed_time":20.60944828,"remaining_time":5.812921311},
{"learn":[0.6663332305],"iteration":780,"passed_time":20.62552313,"remaining_time":5.783597394},
{"learn":[0.6663181706],"iteration":781,"passed_time":20.64522614,"remaining_time":5.755318795},
{"learn":[0.6662751904],"iteration":782,"passed_time":20.6663677,"remaining_time":5.72746078},
{"learn":[0.666227584],"iteration":783,"passed_time":20.68940911,"remaining_time":5.700143325},
{"learn":[0.666137748],"iteration":784,"passed_time":20.71672393,"remaining_time":5.67400719},
{"learn":[0.6660964897],"iteration":785,"passed_time":20.74028827,"remaining_time":5.646846933},
{"learn":[0.6660667845],"iteration":786,"passed_time":20.7614817,"remaining_time":5.619054133},
{"learn":[0.6660543988],"iteration":787,"passed_time":20.78446985,"remaining_time":5.591760923},
{"learn":[0.6659807392],"iteration":788,"passed_time":20.8050653,"remaining_time":5.563838755},
{"learn":[0.6659776465],"iteration":789,"passed_time":20.82555146,"remaining_time":5.535906084},
{"learn":[0.6659551165],"iteration":790,"passed_time":20.84634669,"remaining_time":5.508073905},
{"learn":[0.6658817967],"iteration":791,"passed_time":20.86542458,"remaining_time":5.479808475},
{"learn":[0.6658131524],"iteration":792,"passed_time":20.88859079,"remaining_time":5.45263341},
{"learn":[0.6657019303],"iteration":793,"passed_time":20.90967259,"remaining_time":5.424927651},
{"learn":[0.6656817259],"iteration":794,"passed_time":20.93131465,"remaining_time":5.397383024},
{"learn":[0.6655788262],"iteration":795,"passed_time":20.95106801,"remaining_time":5.36936919},
{"learn":[0.6655632014],"iteration":796,"passed_time":20.97166553,"remaining_time":5.341591094},
{"learn":[0.6655033238],"iteration":797,"passed_time":20.99392911,"remaining_time":5.314252732},
{"learn":[0.6654824118],"iteration":798,"passed_time":21.01422662,"remaining_time":5.286432479},
{"learn":[0.6654503645],"iteration":799,"passed_time":21.03407366,"remaining_time":5.258518416},
{"learn":[0.6654410765],"iteration":800,"passed_time":21.05365441,"remaining_time":5.230558336},
{"learn":[0.6653062462],"iteration":801,"passed_time":21.07589217,"remaining_time":5.203275125},
{"learn":[0.6652953014],"iteration":802,"passed_time":21.09681677,"remaining_time":5.17568232},
{"learn":[0.6652577449],"iteration":803,"passed_time":21.12010618,"remaining_time":5.148682602},
{"learn":[0.6652463825],"iteration":804,"passed_time":21.14013335,"remaining_time":5.120901868},
{"learn":[0.6652304935],"iteration":805,"passed_time":21.15891141,"remaining_time":5.092839719},
{"learn":[0.665225698],"iteration":806,"passed_time":21.17583724,"remaining_time":5.064357606},
{"learn":[0.6650426529],"iteration":807,"passed_time":21.19752513,"remaining_time":5.037035674},
{"learn":[0.6649914266],"iteration":808,"passed_time":21.21942639,"remaining_time":5.009778047},
{"learn":[0.664961016],"iteration":809,"passed_time":21.24084266,"remaining_time":4.982419884},
{"learn":[0.6649402436],"iteration":810,"passed_time":21.26126458,"remaining_time":4.954844644},
{"learn":[0.6648389379],"iteration":811,"passed_time":21.28543141,"remaining_time":4.92815407},
{"learn":[0.664777418],"iteration":812,"passed_time":21.30662846,"remaining_time":4.90078662},
{"learn":[0.6647484844],"iteration":813,"passed_time":21.32791727,"remaining_time":4.873455298},
{"learn":[0.6646622361],"iteration":814,"passed_time":21.34848636,"remaining_time":4.845975431},
{"learn":[0.6646555493],"iteration":815,"passed_time":21.36717742,"remaining_time":4.818089025},
{"learn":[0.6646125151],"iteration":816,"passed_time":21.38751591,"remaining_time":4.79059414},
{"learn":[0.6645373597],"iteration":817,"passed_time":21.40940164,"remaining_time":4.763461002},
{"learn":[0.6642412705],"iteration":818,"passed_time":21.43271247,"remaining_time":4.736655625},
{"learn":[0.6641816162],"iteration":819,"passed_time":21.45511415,"remaining_time":4.709659203},
{"learn":[0.664160513],"iteration":820,"passed_time":21.47954256,"remaining_time":4.683115856},
{"learn":[0.6641254643],"iteration":821,"passed_time":21.50158372,"remaining_time":4.656060709},
{"learn":[0.6640405269],"iteration":822,"passed_time":21.52015222,"remaining_time":4.628270891},
{"learn":[0.66398355],"iteration":823,"passed_time":21.53838243,"remaining_time":4.600431198},
{"learn":[0.6639435718],"iteration":824,"passed_time":21.56126759,"remaining_time":4.573602217},
{"learn":[0.6639128072],"iteration":825,"passed_time":21.58072286,"remaining_time":4.546060263},
{"learn":[0.6638770356],"iteration":826,"passed_time":21.60260854,"remaining_time":4.519046284},
{"learn":[0.6638482369],"iteration":827,"passed_time":21.62552912,"remaining_time":4.492259672},
{"learn":[0.6638300563],"iteration":828,"passed_time":21.64593191,"remaining_time":4.464963036},
{"learn":[0.6636724199],"iteration":829,"passed_time":21.66508408,"remaining_time":4.43742686},
{"learn":[0.6636039257],"iteration":830,"passed_time":21.68756069,"remaining_time":4.410586951},
{"learn":[0.6634612397],"iteration":831,"passed_time":21.70860886,"remaining_time":4.383469097},
{"learn":[0.6634295577],"iteration":832,"passed_time":21.72959095,"remaining_time":4.356352568},
{"learn":[0.6634096334],"iteration":833,"passed_time":21.74781894,"remaining_time":4.32870257},
{"learn":[0.6633908586],"iteration":834,"passed_time":21.76759483,"remaining_time":4.301381015},
{"learn":[0.6633642711],"iteration":835,"passed_time":21.78905299,"remaining_time":4.274407525},
{"learn":[0.6633408947],"iteration":836,"passed_time":21.81024869,"remaining_time":4.247396101},
{"learn":[0.6631560151],"iteration":837,"passed_time":21.82989421,"remaining_time":4.22009888},
{"learn":[0.6631151324],"iteration":838,"passed_time":21.85003393,"remaining_time":4.192914735},
{"learn":[0.6629684646],"iteration":839,"passed_time":21.87018329,"remaining_time":4.165749199},
{"learn":[0.6629489399],"iteration":840,"passed_time":21.89029511,"remaining_time":4.13859325},
{"learn":[0.662919565],"iteration":841,"passed_time":21.91312928,"remaining_time":4.111964876},
{"learn":[0.6629002642],"iteration":842,"passed_time":21.93316683,"remaining_time":4.084824665},
{"learn":[0.6626926891],"iteration":843,"passed_time":21.950835,"remaining_time":4.057263342},
{"learn":[0.6626804475],"iteration":844,"passed_time":21.97455407,"remaining_time":4.030835361},
{"learn":[0.66264921],"iteration":845,"passed_time":21.99761175,"remaining_time":4.004293392},
{"learn":[0.662644929],"iteration":846,"passed_time":22.0177634,"remaining_time":3.977234711},
{"learn":[0.662640216],"iteration":847,"passed_time":22.04081152,"remaining_time":3.950711498},
{"learn":[0.6626318348],"iteration":848,"passed_time":22.06187949,"remaining_time":3.923844291},
{"learn":[0.6626060889],"iteration":849,"passed_time":22.08366001,"remaining_time":3.897116472},
{"learn":[0.6624692701],"iteration":850,"passed_time":22.10369716,"remaining_time":3.870095037},
{"learn":[0.6624605748],"iteration":851,"passed_time":22.12472156,"remaining_time":3.843261492},
{"learn":[0.6624534452],"iteration":852,"passed_time":22.14262761,"remaining_time":3.815904173},
{"learn":[0.6624344556],"iteration":853,"passed_time":22.16251956,"remaining_time":3.788908496},
{"learn":[0.6623104679],"iteration":854,"passed_time":22.18251177,"remaining_time":3.761946441},
{"learn":[0.6622803276],"iteration":855,"passed_time":22.20145028,"remaining_time":3.734823411},
{"learn":[0.6622549084],"iteration":856,"passed_time":22.22525497,"remaining_time":3.70853146},
{"learn":[0.6621695407],"iteration":857,"passed_time":22.25788281,"remaining_time":3.683705546},
{"learn":[0.6621444265],"iteration":858,"passed_time":22.28091444,"remaining_time":3.657286306},
{"learn":[0.6620530036],"iteration":859,"passed_time":22.30135202,"remaining_time":3.630452655},
{"learn":[0.6620484768],"iteration":860,"passed_time":22.32117036,"remaining_time":3.603533892},
{"learn":[0.6620362677],"iteration":861,"passed_time":22.34462034,"remaining_time":3.577213},
{"learn":[0.6619994757],"iteration":862,"passed_time":22.36710866,"remaining_time":3.550746102},
{"learn":[0.6618984575],"iteration":863,"passed_time":22.39120767,"remaining_time":3.524541949},
{"learn":[0.6618621145],"iteration":864,"passed_time":22.41405877,"remaining_time":3.4981479},
{"learn":[0.6618313225],"iteration":865,"passed_time":22.43637083,"remaining_time":3.471678628},
{"learn":[0.6617963255],"iteration":866,"passed_time":22.45799033,"remaining_time":3.445112704},
{"learn":[0.6617659138],"iteration":867,"passed_time":22.48172242,"remaining_time":3.418879446},
{"learn":[0.66173266],"iteration":868,"passed_time":22.50560676,"remaining_time":3.392674897},
{"learn":[0.6617151617],"iteration":869,"passed_time":22.53634735,"remaining_time":3.367500179},
{"learn":[0.66168508],"iteration":870,"passed_time":22.55993801,"remaining_time":3.341253735},
{"learn":[0.6616842062],"iteration":871,"passed_time":22.57908383,"remaining_time":3.314360929},
{"learn":[0.6616739641],"iteration":872,"passed_time":22.60008062,"remaining_time":3.287755142},
{"learn":[0.6616207725],"iteration":873,"passed_time":22.62277444,"remaining_time":3.261406841},
{"learn":[0.661595159],"iteration":874,"passed_time":22.64268996,"remaining_time":3.234669994},
{"learn":[0.6615871082],"iteration":875,"passed_time":22.66428523,"remaining_time":3.208186494},
{"learn":[0.6615590551],"iteration":876,"passed_time":22.68505309,"remaining_time":3.181598096},
{"learn":[0.6614508629],"iteration":877,"passed_time":22.70560989,"remaining_time":3.154993629},
{"learn":[0.6614468042],"iteration":878,"passed_time":22.72362025,"remaining_time":3.128052389},
{"learn":[0.6614050236],"iteration":879,"passed_time":22.74343052,"remaining_time":3.101376889},
{"learn":[0.6613762341],"iteration":880,"passed_time":22.76584753,"remaining_time":3.075069076},
{"learn":[0.6613356615],"iteration":881,"passed_time":22.78473493,"remaining_time":3.048297871},
{"learn":[0.6613249149],"iteration":882,"passed_time":22.81245147,"remaining_time":3.022714408},
{"learn":[0.6613097078],"iteration":883,"passed_time":22.83942535,"remaining_time":2.997028665},
{"learn":[0.6612463308],"iteration":884,"passed_time":22.86336552,"remaining_time":2.970945802},
{"learn":[0.6611321483],"iteration":885,"passed_time":22.88847749,"remaining_time":2.945018548},
{"learn":[0.6610863299],"iteration":886,"passed_time":22.90977739,"remaining_time":2.918607492},
{"learn":[0.6610821896],"iteration":887,"passed_time":22.93153495,"remaining_time":2.89226567},
{"learn":[0.6610423814],"iteration":888,"passed_time":22.9575213,"remaining_time":2.866462165},
{"learn":[0.6609423539],"iteration":889,"passed_time":22.97830874,"remaining_time":2.840015687},
{"learn":[0.6608722576],"iteration":890,"passed_time":23.00287373,"remaining_time":2.814044036},
{"learn":[0.660786416],"iteration":891,"passed_time":23.03026769,"remaining_time":2.788418061},
{"learn":[0.6607365876],"iteration":892,"passed_time":23.05307274,"remaining_time":2.762238279},
{"learn":[0.6606973162],"iteration":893,"passed_time":23.07954813,"remaining_time":2.736501232},
{"learn":[0.6606577424],"iteration":894,"passed_time":23.1123508,"remaining_time":2.711504843},
{"learn":[0.6605975811],"iteration":895,"passed_time":23.13583834,"remaining_time":2.685409807},
{"learn":[0.6605755866],"iteration":896,"passed_time":23.1574061,"remaining_time":2.659100143},
{"learn":[0.6605640715],"iteration":897,"passed_time":23.17683664,"remaining_time":2.632558282},
{"learn":[0.6605601884],"iteration":898,"passed_time":23.19764319,"remaining_time":2.606186832},
{"learn":[0.6604695701],"iteration":899,"passed_time":23.22137369,"remaining_time":2.580152632},
{"learn":[0.6604601913],"iteration":900,"passed_time":23.24126246,"remaining_time":2.553701424},
{"learn":[0.6604570187],"iteration":901,"passed_time":23.25982555,"remaining_time":2.527120736},
{"learn":[0.6604129254],"iteration":902,"passed_time":23.28106444,"remaining_time":2.500845239},
{"learn":[0.6604079834],"iteration":903,"passed_time":23.30060218,"remaining_time":2.474400231},
{"learn":[0.6603971853],"iteration":904,"passed_time":23.32189925,"remaining_time":2.44815517},
{"learn":[0.6603935073],"iteration":905,"passed_time":23.34212947,"remaining_time":2.421810343},
{"learn":[0.6603770687],"iteration":906,"passed_time":23.35700922,"remaining_time":2.394930383},
{"learn":[0.6603023231],"iteration":907,"passed_time":23.38028871,"remaining_time":2.368927931},
{"learn":[0.66024808],"iteration":908,"passed_time":23.40360907,"remaining_time":2.342935561},
{"learn":[0.6602152898],"iteration":909,"passed_time":23.42781033,"remaining_time":2.317036187},
{"learn":[0.6601529338],"iteration":910,"passed_time":23.44918126,"remaining_time":2.290864031},
{"learn":[0.6600989889],"iteration":911,"passed_time":23.46924725,"remaining_time":2.264576489},
{"learn":[0.6600201911],"iteration":912,"passed_time":23.49210195,"remaining_time":2.238568313},
{"learn":[0.6599986602],"iteration":913,"passed_time":23.51354554,"remaining_time":2.212434263},
{"learn":[0.6599877162],"iteration":914,"passed_time":23.53380298,"remaining_time":2.186200277},
{"learn":[0.6599581477],"iteration":915,"passed_time":23.55787492,"remaining_time":2.160329141},
{"learn":[0.6599419012],"iteration":916,"passed_time":23.57914973,"remaining_time":2.134208754},
{"learn":[0.6599318899],"iteration":917,"passed_time":23.60118467,"remaining_time":2.108166822},
{"learn":[0.6598682254],"iteration":918,"passed_time":23.6230621,"remaining_time":2.082119728},
{"learn":[0.6598191898],"iteration":919,"passed_time":23.64075425,"remaining_time":2.055717761},
{"learn":[0.6597084198],"iteration":920,"passed_time":23.67678216,"remaining_time":2.030907481},
{"learn":[0.6596906448],"iteration":921,"passed_time":23.70211913,"remaining_time":2.00516843},
{"learn":[0.6596757168],"iteration":922,"passed_time":23.72640183,"remaining_time":1.979342298},
{"learn":[0.6595594178],"iteration":923,"passed_time":23.7517485,"remaining_time":1.95360702},
{"learn":[0.6595396533],"iteration":924,"passed_time":23.77674137,"remaining_time":1.927843895},
{"learn":[0.6594413589],"iteration":925,"passed_time":23.80038738,"remaining_time":1.901974802},
{"learn":[0.6594303601],"iteration":926,"passed_time":23.82249384,"remaining_time":1.875989267},
{"learn":[0.6594196952],"iteration":927,"passed_time":23.8430751,"remaining_time":1.849893757},
{"learn":[0.6593728016],"iteration":928,"passed_time":23.86405005,"remaining_time":1.823840209},
{"learn":[0.6593480884],"iteration":929,"passed_time":23.8866731,"remaining_time":1.797921631},
{"learn":[0.6593447931],"iteration":930,"passed_time":23.90479592,"remaining_time":1.771676604},
{"learn":[0.6593029548],"iteration":931,"passed_time":23.92840786,"remaining_time":1.7458495},
{"learn":[0.6592714811],"iteration":932,"passed_time":23.95123174,"remaining_time":1.719970554},
{"learn":[0.6592194127],"iteration":933,"passed_time":23.97122763,"remaining_time":1.693898312},
{"learn":[0.6591984961],"iteration":934,"passed_time":23.99272503,"remaining_time":1.667943452},
{"learn":[0.6591618948],"iteration":935,"passed_time":24.01263641,"remaining_time":1.641889669},
{"learn":[0.6591592709],"iteration":936,"passed_time":24.02984233,"remaining_time":1.615667094},
{"learn":[0.6590380831],"iteration":937,"passed_time":24.05144833,"remaining_time":1.589754581},
{"learn":[0.6589927092],"iteration":938,"passed_time":24.07197874,"remaining_time":1.563781366},
{"learn":[0.6589765073],"iteration":939,"passed_time":24.09540002,"remaining_time":1.538004256},
{"learn":[0.658898954],"iteration":940,"passed_time":24.11555877,"remaining_time":1.512027596},
{"learn":[0.658862009],"iteration":941,"passed_time":24.1370785,"remaining_time":1.486147084},
{"learn":[0.6588114742],"iteration":942,"passed_time":24.15744675,"remaining_time":1.460206219},
{"learn":[0.6587691267],"iteration":943,"passed_time":24.1772548,"remaining_time":1.434243929},
{"learn":[0.6586818052],"iteration":944,"passed_time":24.1961529,"remaining_time":1.408241703},
{"learn":[0.6586518013],"iteration":945,"passed_time":24.21938672,"remaining_time":1.382501991},
{"learn":[0.6585761547],"iteration":946,"passed_time":24.2397096,"remaining_time":1.356604656},
{"learn":[0.6585216081],"iteration":947,"passed_time":24.26040997,"remaining_time":1.330739788},
{"learn":[0.6585127617],"iteration":948,"passed_time":24.28179167,"remaining_time":1.304922418},
{"learn":[0.6584942113],"iteration":949,"passed_time":24.30362009,"remaining_time":1.2791379},
{"learn":[0.6584740782],"iteration":950,"passed_time":24.32296212,"remaining_time":1.25323359},
{"learn":[0.6584304759],"iteration":951,"passed_time":24.3455889,"remaining_time":1.227508684},
{"learn":[0.6584228868],"iteration":952,"passed_time":24.36716495,"remaining_time":1.20173846},
{"learn":[0.6583295977],"iteration":953,"passed_time":24.38764777,"remaining_time":1.175924316},
{"learn":[0.6582939308],"iteration":954,"passed_time":24.40885406,"remaining_time":1.150155427},
{"learn":[0.6582840174],"iteration":955,"passed_time":24.43062232,"remaining_time":1.124421948},
{"learn":[0.6582750605],"iteration":956,"passed_time":24.44984808,"remaining_time":1.098582516},
{"learn":[0.6582558676],"iteration":957,"passed_time":24.46863292,"remaining_time":1.07273756},
{"learn":[0.6582217666],"iteration":958,"passed_time":24.48921466,"remaining_time":1.046984151},
{"learn":[0.6582056636],"iteration":959,"passed_time":24.51211167,"remaining_time":1.021337986},
{"learn":[0.658191941],"iteration":960,"passed_time":24.53150251,"remaining_time":0.9955552527},
{"learn":[0.6581607633],"iteration":961,"passed_time":24.55314664,"remaining_time":0.9698748154},
{"learn":[0.6581236195],"iteration":962,"passed_time":24.57423376,"remaining_time":0.9441813596},
{"learn":[0.6580837511],"iteration":963,"passed_time":24.59228798,"remaining_time":0.9183841984},
{"learn":[0.6580369559],"iteration":964,"passed_time":24.61244714,"remaining_time":0.8926794298},
{"learn":[0.658011058],"iteration":965,"passed_time":24.63772432,"remaining_time":0.8671662804},
{"learn":[0.6579933579],"iteration":966,"passed_time":24.65515806,"remaining_time":0.8413859525},
{"learn":[0.657925589],"iteration":967,"passed_time":24.67799448,"remaining_time":0.8158014703},
{"learn":[0.6579084544],"iteration":968,"passed_time":24.69781132,"remaining_time":0.7901260588},
{"learn":[0.6578844743],"iteration":969,"passed_time":24.71817821,"remaining_time":0.7644797384},
{"learn":[0.6578644094],"iteration":970,"passed_time":24.7408783,"remaining_time":0.738913976},
{"learn":[0.6578552782],"iteration":971,"passed_time":24.75790295,"remaining_time":0.7131906201},
{"learn":[0.6578527072],"iteration":972,"passed_time":24.77559881,"remaining_time":0.6875037697},
{"learn":[0.6578367917],"iteration":973,"passed_time":24.79724106,"remaining_time":0.6619386731},
{"learn":[0.6578085413],"iteration":974,"passed_time":24.82068761,"remaining_time":0.6364278874},
{"learn":[0.6577869518],"iteration":975,"passed_time":24.84116336,"remaining_time":0.6108482794},
{"learn":[0.6577621682],"iteration":976,"passed_time":24.86189816,"remaining_time":0.5852852178},
{"learn":[0.657742802],"iteration":977,"passed_time":24.88458039,"remaining_time":0.5597758371},
{"learn":[0.6577229025],"iteration":978,"passed_time":24.90367229,"remaining_time":0.5341952176},
{"learn":[0.6577182424],"iteration":979,"passed_time":24.92267468,"remaining_time":0.5086260138},
{"learn":[0.6577037788],"iteration":980,"passed_time":24.94228387,"remaining_time":0.4830819506},
{"learn":[0.6576936538],"iteration":981,"passed_time":24.96445563,"remaining_time":0.4575969464},
{"learn":[0.6576420768],"iteration":982,"passed_time":24.98445858,"remaining_time":0.4320811759},
{"learn":[0.657620448],"iteration":983,"passed_time":25.00827026,"remaining_time":0.4066385408},
{"learn":[0.6575618935],"iteration":984,"passed_time":25.03131824,"remaining_time":0.3811875874},
{"learn":[0.6575384596],"iteration":985,"passed_time":25.05713652,"remaining_time":0.3557808431},
{"learn":[0.6575168268],"iteration":986,"passed_time":25.08001511,"remaining_time":0.3303345456},
{"learn":[0.6574327138],"iteration":987,"passed_time":25.09994217,"remaining_time":0.3048575973},
{"learn":[0.6574283854],"iteration":988,"passed_time":25.11761933,"remaining_time":0.279366848},
{"learn":[0.657422367],"iteration":989,"passed_time":25.13362997,"remaining_time":0.2538750502},
{"learn":[0.6574078503],"iteration":990,"passed_time":25.15133198,"remaining_time":0.2284177476},
{"learn":[0.6573789233],"iteration":991,"passed_time":25.1724468,"remaining_time":0.2030036032},
{"learn":[0.657346313],"iteration":992,"passed_time":25.19212983,"remaining_time":0.177588025},
{"learn":[0.6572857926],"iteration":993,"passed_time":25.20371081,"remaining_time":0.1521350753},
{"learn":[0.6572439373],"iteration":994,"passed_time":25.21173462,"remaining_time":0.1266921338},
{"learn":[0.6572347405],"iteration":995,"passed_time":25.21818713,"remaining_time":0.1012778599},
{"learn":[0.657201175],"iteration":996,"passed_time":25.22483312,"remaining_time":0.07590220598},
{"learn":[0.6571696514],"iteration":997,"passed_time":25.2318547,"remaining_time":0.05056483907},
{"learn":[0.6571326989],"iteration":998,"passed_time":25.23998026,"remaining_time":0.02526524551},
{"learn":[0.6570609018],"iteration":999,"passed_time":25.25124598,"remaining_time":0}
]}}ng_time":0}
]}